{"nodes": [{"id": "d_excel_add_in_v2_sources_officecli_main_officecli_main_src_officecli_mcpinstaller_cs", "label": "McpInstaller.cs", "file_type": "code", "source_file": "D:\\Excel Add-in V2\\sources\\OfficeCLI-main\\OfficeCLI-main\\src\\officecli\\McpInstaller.cs", "source_location": "L1"}, {"id": "mcpinstaller_mcpinstaller", "label": "McpInstaller", "file_type": "code", "source_file": "D:\\Excel Add-in V2\\sources\\OfficeCLI-main\\OfficeCLI-main\\src\\officecli\\McpInstaller.cs", "source_location": "L11"}, {"id": "mcpinstaller_mcpinstaller_install", "label": ".Install()", "file_type": "code", "source_file": "D:\\Excel Add-in V2\\sources\\OfficeCLI-main\\OfficeCLI-main\\src\\officecli\\McpInstaller.cs", "source_location": "L16"}, {"id": "mcpinstaller_mcpinstaller_uninstall", "label": ".Uninstall()", "file_type": "code", "source_file": "D:\\Excel Add-in V2\\sources\\OfficeCLI-main\\OfficeCLI-main\\src\\officecli\\McpInstaller.cs", "source_location": "L47"}, {"id": "mcpinstaller_mcpinstaller_installlmstudio", "label": ".InstallLmStudio()", "file_type": "code", "source_file": "D:\\Excel Add-in V2\\sources\\OfficeCLI-main\\OfficeCLI-main\\src\\officecli\\McpInstaller.cs", "source_location": "L71"}, {"id": "mcpinstaller_mcpinstaller_uninstalllmstudio", "label": ".UninstallLmStudio()", "file_type": "code", "source_file": "D:\\Excel Add-in V2\\sources\\OfficeCLI-main\\OfficeCLI-main\\src\\officecli\\McpInstaller.cs", "source_location": "L94"}, {"id": "mcpinstaller_mcpinstaller_getclaudesettingspath", "label": ".GetClaudeSettingsPath()", "file_type": "code", "source_file": "D:\\Excel Add-in V2\\sources\\OfficeCLI-main\\OfficeCLI-main\\src\\officecli\\McpInstaller.cs", "source_location": "L112"}, {"id": "mcpinstaller_mcpinstaller_installclaude", "label": ".InstallClaude()", "file_type": "code", "source_file": "D:\\Excel Add-in V2\\sources\\OfficeCLI-main\\OfficeCLI-main\\src\\officecli\\McpInstaller.cs", "source_location": "L115"}, {"id": "mcpinstaller_mcpinstaller_getcursormcppath", "label": ".GetCursorMcpPath()", "file_type": "code", "source_file": "D:\\Excel Add-in V2\\sources\\OfficeCLI-main\\OfficeCLI-main\\src\\officecli\\McpInstaller.cs", "source_location": "L120"}, {"id": "mcpinstaller_mcpinstaller_installcursor", "label": ".InstallCursor()", "file_type": "code", "source_file": "D:\\Excel Add-in V2\\sources\\OfficeCLI-main\\OfficeCLI-main\\src\\officecli\\McpInstaller.cs", "source_location": "L123"}, {"id": "mcpinstaller_mcpinstaller_getvscodemcppath", "label": ".GetVsCodeMcpPath()", "file_type": "code", "source_file": "D:\\Excel Add-in V2\\sources\\OfficeCLI-main\\OfficeCLI-main\\src\\officecli\\McpInstaller.cs", "source_location": "L128"}, {"id": "mcpinstaller_mcpinstaller_installvscode", "label": ".InstallVsCode()", "file_type": "code", "source_file": "D:\\Excel Add-in V2\\sources\\OfficeCLI-main\\OfficeCLI-main\\src\\officecli\\McpInstaller.cs", "source_location": "L131"}, {"id": "mcpinstaller_mcpinstaller_installjson", "label": ".InstallJson()", "file_type": "code", "source_file": "D:\\Excel Add-in V2\\sources\\OfficeCLI-main\\OfficeCLI-main\\src\\officecli\\McpInstaller.cs", "source_location": "L136"}, {"id": "mcpinstaller_mcpinstaller_writeserversdict", "label": ".WriteServersDict()", "file_type": "code", "source_file": "D:\\Excel Add-in V2\\sources\\OfficeCLI-main\\OfficeCLI-main\\src\\officecli\\McpInstaller.cs", "source_location": "L191"}, {"id": "mcpinstaller_mcpinstaller_uninstalljson", "label": ".UninstallJson()", "file_type": "code", "source_file": "D:\\Excel Add-in V2\\sources\\OfficeCLI-main\\OfficeCLI-main\\src\\officecli\\McpInstaller.cs", "source_location": "L212"}, {"id": "mcpinstaller_mcpinstaller_liststatus", "label": ".ListStatus()", "file_type": "code", "source_file": "D:\\Excel Add-in V2\\sources\\OfficeCLI-main\\OfficeCLI-main\\src\\officecli\\McpInstaller.cs", "source_location": "L261"}, {"id": "mcpinstaller_mcpinstaller_checkstatus", "label": ".CheckStatus()", "file_type": "code", "source_file": "D:\\Excel Add-in V2\\sources\\OfficeCLI-main\\OfficeCLI-main\\src\\officecli\\McpInstaller.cs", "source_location": "L279"}, {"id": "mcpinstaller_mcpinstaller_checkjsonstatus", "label": ".CheckJsonStatus()", "file_type": "code", "source_file": "D:\\Excel Add-in V2\\sources\\OfficeCLI-main\\OfficeCLI-main\\src\\officecli\\McpInstaller.cs", "source_location": "L285"}, {"id": "mcpinstaller_mcpinstaller_escapejson", "label": ".EscapeJson()", "file_type": "code", "source_file": "D:\\Excel Add-in V2\\sources\\OfficeCLI-main\\OfficeCLI-main\\src\\officecli\\McpInstaller.cs", "source_location": "L301"}, {"id": "mcpinstaller_mcpserverentry", "label": "McpServerEntry", "file_type": "code", "source_file": "D:\\Excel Add-in V2\\sources\\OfficeCLI-main\\OfficeCLI-main\\src\\officecli\\McpInstaller.cs", "source_location": "L303"}], "edges": [{"source": "d_excel_add_in_v2_sources_officecli_main_officecli_main_src_officecli_mcpinstaller_cs", "target": "json", "relation": "imports", "confidence": "EXTRACTED", "source_file": "D:\\Excel Add-in V2\\sources\\OfficeCLI-main\\OfficeCLI-main\\src\\officecli\\McpInstaller.cs", "source_location": "L4", "weight": 1.0}, {"source": "d_excel_add_in_v2_sources_officecli_main_officecli_main_src_officecli_mcpinstaller_cs", "target": "mcpinstaller_mcpinstaller", "relation": "contains", "confidence": "EXTRACTED", "source_file": "D:\\Excel Add-in V2\\sources\\OfficeCLI-main\\OfficeCLI-main\\src\\officecli\\McpInstaller.cs", "source_location": "L11", "weight": 1.0}, {"source": "mcpinstaller_mcpinstaller", "target": "mcpinstaller_mcpinstaller_install", "relation": "method", "confidence": "EXTRACTED", "source_file": "D:\\Excel Add-in V2\\sources\\OfficeCLI-main\\OfficeCLI-main\\src\\officecli\\McpInstaller.cs", "source_location": "L16", "weight": 1.0}, {"source": "mcpinstaller_mcpinstaller", "target": "mcpinstaller_mcpinstaller_uninstall", "relation": "method", "confidence": "EXTRACTED", "source_file": "D:\\Excel Add-in V2\\sources\\OfficeCLI-main\\OfficeCLI-main\\src\\officecli\\McpInstaller.cs", "source_location": "L47", "weight": 1.0}, {"source": "mcpinstaller_mcpinstaller", "target": "mcpinstaller_mcpinstaller_installlmstudio", "relation": "method", "confidence": "EXTRACTED", "source_file": "D:\\Excel Add-in V2\\sources\\OfficeCLI-main\\OfficeCLI-main\\src\\officecli\\McpInstaller.cs", "source_location": "L71", "weight": 1.0}, {"source": "mcpinstaller_mcpinstaller", "target": "mcpinstaller_mcpinstaller_uninstalllmstudio", "relation": "method", "confidence": "EXTRACTED", "source_file": "D:\\Excel Add-in V2\\sources\\OfficeCLI-main\\OfficeCLI-main\\src\\officecli\\McpInstaller.cs", "source_location": "L94", "weight": 1.0}, {"source": "mcpinstaller_mcpinstaller", "target": "mcpinstaller_mcpinstaller_getclaudesettingspath", "relation": "method", "confidence": "EXTRACTED", "source_file": "D:\\Excel Add-in V2\\sources\\OfficeCLI-main\\OfficeCLI-main\\src\\officecli\\McpInstaller.cs", "source_location": "L112", "weight": 1.0}, {"source": "mcpinstaller_mcpinstaller", "target": "mcpinstaller_mcpinstaller_installclaude", "relation": "method", "confidence": "EXTRACTED", "source_file": "D:\\Excel Add-in V2\\sources\\OfficeCLI-main\\OfficeCLI-main\\src\\officecli\\McpInstaller.cs", "source_location": "L115", "weight": 1.0}, {"source": "mcpinstaller_mcpinstaller", "target": "mcpinstaller_mcpinstaller_getcursormcppath", "relation": "method", "confidence": "EXTRACTED", "source_file": "D:\\Excel Add-in V2\\sources\\OfficeCLI-main\\OfficeCLI-main\\src\\officecli\\McpInstaller.cs", "source_location": "L120", "weight": 1.0}, {"source": "mcpinstaller_mcpinstaller", "target": "mcpinstaller_mcpinstaller_installcursor", "relation": "method", "confidence": "EXTRACTED", "source_file": "D:\\Excel Add-in V2\\sources\\OfficeCLI-main\\OfficeCLI-main\\src\\officecli\\McpInstaller.cs", "source_location": "L123", "weight": 1.0}, {"source": "mcpinstaller_mcpinstaller", "target": "mcpinstaller_mcpinstaller_getvscodemcppath", "relation": "method", "confidence": "EXTRACTED", "source_file": "D:\\Excel Add-in V2\\sources\\OfficeCLI-main\\OfficeCLI-main\\src\\officecli\\McpInstaller.cs", "source_location": "L128", "weight": 1.0}, {"source": "mcpinstaller_mcpinstaller", "target": "mcpinstaller_mcpinstaller_installvscode", "relation": "method", "confidence": "EXTRACTED", "source_file": "D:\\Excel Add-in V2\\sources\\OfficeCLI-main\\OfficeCLI-main\\src\\officecli\\McpInstaller.cs", "source_location": "L131", "weight": 1.0}, {"source": "mcpinstaller_mcpinstaller", "target": "mcpinstaller_mcpinstaller_installjson", "relation": "method", "confidence": "EXTRACTED", "source_file": "D:\\Excel Add-in V2\\sources\\OfficeCLI-main\\OfficeCLI-main\\src\\officecli\\McpInstaller.cs", "source_location": "L136", "weight": 1.0}, {"source": "mcpinstaller_mcpinstaller", "target": "mcpinstaller_mcpinstaller_writeserversdict", "relation": "method", "confidence": "EXTRACTED", "source_file": "D:\\Excel Add-in V2\\sources\\OfficeCLI-main\\OfficeCLI-main\\src\\officecli\\McpInstaller.cs", "source_location": "L191", "weight": 1.0}, {"source": "mcpinstaller_mcpinstaller", "target": "mcpinstaller_mcpinstaller_uninstalljson", "relation": "method", "confidence": "EXTRACTED", "source_file": "D:\\Excel Add-in V2\\sources\\OfficeCLI-main\\OfficeCLI-main\\src\\officecli\\McpInstaller.cs", "source_location": "L212", "weight": 1.0}, {"source": "mcpinstaller_mcpinstaller", "target": "mcpinstaller_mcpinstaller_liststatus", "relation": "method", "confidence": "EXTRACTED", "source_file": "D:\\Excel Add-in V2\\sources\\OfficeCLI-main\\OfficeCLI-main\\src\\officecli\\McpInstaller.cs", "source_location": "L261", "weight": 1.0}, {"source": "mcpinstaller_mcpinstaller", "target": "mcpinstaller_mcpinstaller_checkstatus", "relation": "method", "confidence": "EXTRACTED", "source_file": "D:\\Excel Add-in V2\\sources\\OfficeCLI-main\\OfficeCLI-main\\src\\officecli\\McpInstaller.cs", "source_location": "L279", "weight": 1.0}, {"source": "mcpinstaller_mcpinstaller", "target": "mcpinstaller_mcpinstaller_checkjsonstatus", "relation": "method", "confidence": "EXTRACTED", "source_file": "D:\\Excel Add-in V2\\sources\\OfficeCLI-main\\OfficeCLI-main\\src\\officecli\\McpInstaller.cs", "source_location": "L285", "weight": 1.0}, {"source": "mcpinstaller_mcpinstaller", "target": "mcpinstaller_mcpinstaller_escapejson", "relation": "method", "confidence": "EXTRACTED", "source_file": "D:\\Excel Add-in V2\\sources\\OfficeCLI-main\\OfficeCLI-main\\src\\officecli\\McpInstaller.cs", "source_location": "L301", "weight": 1.0}, {"source": "d_excel_add_in_v2_sources_officecli_main_officecli_main_src_officecli_mcpinstaller_cs", "target": "mcpinstaller_mcpserverentry", "relation": "contains", "confidence": "EXTRACTED", "source_file": "D:\\Excel Add-in V2\\sources\\OfficeCLI-main\\OfficeCLI-main\\src\\officecli\\McpInstaller.cs", "source_location": "L303", "weight": 1.0}, {"source": "mcpinstaller_mcpinstaller_install", "target": "mcpinstaller_mcpinstaller_installlmstudio", "relation": "calls", "confidence": "EXTRACTED", "source_file": "D:\\Excel Add-in V2\\sources\\OfficeCLI-main\\OfficeCLI-main\\src\\officecli\\McpInstaller.cs", "source_location": "L21", "weight": 1.0}, {"source": "mcpinstaller_mcpinstaller_install", "target": "mcpinstaller_mcpinstaller_installclaude", "relation": "calls", "confidence": "EXTRACTED", "source_file": "D:\\Excel Add-in V2\\sources\\OfficeCLI-main\\OfficeCLI-main\\src\\officecli\\McpInstaller.cs", "source_location": "L24", "weight": 1.0}, {"source": "mcpinstaller_mcpinstaller_install", "target": "mcpinstaller_mcpinstaller_installcursor", "relation": "calls", "confidence": "EXTRACTED", "source_file": "D:\\Excel Add-in V2\\sources\\OfficeCLI-main\\OfficeCLI-main\\src\\officecli\\McpInstaller.cs", "source_location": "L27", "weight": 1.0}, {"source": "mcpinstaller_mcpinstaller_install", "target": "mcpinstaller_mcpinstaller_installvscode", "relation": "calls", "confidence": "EXTRACTED", "source_file": "D:\\Excel Add-in V2\\sources\\OfficeCLI-main\\OfficeCLI-main\\src\\officecli\\McpInstaller.cs", "source_location": "L30", "weight": 1.0}, {"source": "mcpinstaller_mcpinstaller_install", "target": "mcpinstaller_mcpinstaller_liststatus", "relation": "calls", "confidence": "EXTRACTED", "source_file": "D:\\Excel Add-in V2\\sources\\OfficeCLI-main\\OfficeCLI-main\\src\\officecli\\McpInstaller.cs", "source_location": "L33", "weight": 1.0}, {"source": "mcpinstaller_mcpinstaller_uninstall", "target": "mcpinstaller_mcpinstaller_uninstalllmstudio", "relation": "calls", "confidence": "EXTRACTED", "source_file": "D:\\Excel Add-in V2\\sources\\OfficeCLI-main\\OfficeCLI-main\\src\\officecli\\McpInstaller.cs", "source_location": "L52", "weight": 1.0}, {"source": "mcpinstaller_mcpinstaller_uninstall", "target": "mcpinstaller_mcpinstaller_uninstalljson", "relation": "calls", "confidence": "EXTRACTED", "source_file": "D:\\Excel Add-in V2\\sources\\OfficeCLI-main\\OfficeCLI-main\\src\\officecli\\McpInstaller.cs", "source_location": "L55", "weight": 1.0}, {"source": "mcpinstaller_mcpinstaller_uninstall", "target": "mcpinstaller_mcpinstaller_getclaudesettingspath", "relation": "calls", "confidence": "EXTRACTED", "source_file": "D:\\Excel Add-in V2\\sources\\OfficeCLI-main\\OfficeCLI-main\\src\\officecli\\McpInstaller.cs", "source_location": "L55", "weight": 1.0}, {"source": "mcpinstaller_mcpinstaller_uninstall", "target": "mcpinstaller_mcpinstaller_getcursormcppath", "relation": "calls", "confidence": "EXTRACTED", "source_file": "D:\\Excel Add-in V2\\sources\\OfficeCLI-main\\OfficeCLI-main\\src\\officecli\\McpInstaller.cs", "source_location": "L58", "weight": 1.0}, {"source": "mcpinstaller_mcpinstaller_uninstall", "target": "mcpinstaller_mcpinstaller_getvscodemcppath", "relation": "calls", "confidence": "EXTRACTED", "source_file": "D:\\Excel Add-in V2\\sources\\OfficeCLI-main\\OfficeCLI-main\\src\\officecli\\McpInstaller.cs", "source_location": "L61", "weight": 1.0}, {"source": "mcpinstaller_mcpinstaller_installlmstudio", "target": "mcpinstaller_mcpinstaller_escapejson", "relation": "calls", "confidence": "EXTRACTED", "source_file": "D:\\Excel Add-in V2\\sources\\OfficeCLI-main\\OfficeCLI-main\\src\\officecli\\McpInstaller.cs", "source_location": "L83", "weight": 1.0}, {"source": "mcpinstaller_mcpinstaller_installclaude", "target": "mcpinstaller_mcpinstaller_installjson", "relation": "calls", "confidence": "EXTRACTED", "source_file": "D:\\Excel Add-in V2\\sources\\OfficeCLI-main\\OfficeCLI-main\\src\\officecli\\McpInstaller.cs", "source_location": "L116", "weight": 1.0}, {"source": "mcpinstaller_mcpinstaller_installclaude", "target": "mcpinstaller_mcpinstaller_getclaudesettingspath", "relation": "calls", "confidence": "EXTRACTED", "source_file": "D:\\Excel Add-in V2\\sources\\OfficeCLI-main\\OfficeCLI-main\\src\\officecli\\McpInstaller.cs", "source_location": "L116", "weight": 1.0}, {"source": "mcpinstaller_mcpinstaller_installcursor", "target": "mcpinstaller_mcpinstaller_installjson", "relation": "calls", "confidence": "EXTRACTED", "source_file": "D:\\Excel Add-in V2\\sources\\OfficeCLI-main\\OfficeCLI-main\\src\\officecli\\McpInstaller.cs", "source_location": "L124", "weight": 1.0}, {"source": "mcpinstaller_mcpinstaller_installcursor", "target": "mcpinstaller_mcpinstaller_getcursormcppath", "relation": "calls", "confidence": "EXTRACTED", "source_file": "D:\\Excel Add-in V2\\sources\\OfficeCLI-main\\OfficeCLI-main\\src\\officecli\\McpInstaller.cs", "source_location": "L124", "weight": 1.0}, {"source": "mcpinstaller_mcpinstaller_installvscode", "target": "mcpinstaller_mcpinstaller_installjson", "relation": "calls", "confidence": "EXTRACTED", "source_file": "D:\\Excel Add-in V2\\sources\\OfficeCLI-main\\OfficeCLI-main\\src\\officecli\\McpInstaller.cs", "source_location": "L132", "weight": 1.0}, {"source": "mcpinstaller_mcpinstaller_installvscode", "target": "mcpinstaller_mcpinstaller_getvscodemcppath", "relation": "calls", "confidence": "EXTRACTED", "source_file": "D:\\Excel Add-in V2\\sources\\OfficeCLI-main\\OfficeCLI-main\\src\\officecli\\McpInstaller.cs", "source_location": "L132", "weight": 1.0}, {"source": "mcpinstaller_mcpinstaller_installjson", "target": "mcpinstaller_mcpinstaller_writeserversdict", "relation": "calls", "confidence": "EXTRACTED", "source_file": "D:\\Excel Add-in V2\\sources\\OfficeCLI-main\\OfficeCLI-main\\src\\officecli\\McpInstaller.cs", "source_location": "L178", "weight": 1.0}, {"source": "mcpinstaller_mcpinstaller_liststatus", "target": "mcpinstaller_mcpinstaller_checkstatus", "relation": "calls", "confidence": "EXTRACTED", "source_file": "D:\\Excel Add-in V2\\sources\\OfficeCLI-main\\OfficeCLI-main\\src\\officecli\\McpInstaller.cs", "source_location": "L266", "weight": 1.0}, {"source": "mcpinstaller_mcpinstaller_liststatus", "target": "mcpinstaller_mcpinstaller_checkjsonstatus", "relation": "calls", "confidence": "EXTRACTED", "source_file": "D:\\Excel Add-in V2\\sources\\OfficeCLI-main\\OfficeCLI-main\\src\\officecli\\McpInstaller.cs", "source_location": "L269", "weight": 1.0}, {"source": "mcpinstaller_mcpinstaller_liststatus", "target": "mcpinstaller_mcpinstaller_getclaudesettingspath", "relation": "calls", "confidence": "EXTRACTED", "source_file": "D:\\Excel Add-in V2\\sources\\OfficeCLI-main\\OfficeCLI-main\\src\\officecli\\McpInstaller.cs", "source_location": "L269", "weight": 1.0}, {"source": "mcpinstaller_mcpinstaller_liststatus", "target": "mcpinstaller_mcpinstaller_getcursormcppath", "relation": "calls", "confidence": "EXTRACTED", "source_file": "D:\\Excel Add-in V2\\sources\\OfficeCLI-main\\OfficeCLI-main\\src\\officecli\\McpInstaller.cs", "source_location": "L270", "weight": 1.0}, {"source": "mcpinstaller_mcpinstaller_liststatus", "target": "mcpinstaller_mcpinstaller_getvscodemcppath", "relation": "calls", "confidence": "EXTRACTED", "source_file": "D:\\Excel Add-in V2\\sources\\OfficeCLI-main\\OfficeCLI-main\\src\\officecli\\McpInstaller.cs", "source_location": "L271", "weight": 1.0}], "raw_calls": [{"caller_nid": "mcpinstaller_mcpinstaller_install", "callee": "ToLowerInvariant", "source_file": "D:\\Excel Add-in V2\\sources\\OfficeCLI-main\\OfficeCLI-main\\src\\officecli\\McpInstaller.cs", "source_location": "L18"}, {"caller_nid": "mcpinstaller_mcpinstaller_install", "callee": "WriteLine", "source_file": "D:\\Excel Add-in V2\\sources\\OfficeCLI-main\\OfficeCLI-main\\src\\officecli\\McpInstaller.cs", "source_location": "L36"}, {"caller_nid": "mcpinstaller_mcpinstaller_install", "callee": "WriteLine", "source_file": "D:\\Excel Add-in V2\\sources\\OfficeCLI-main\\OfficeCLI-main\\src\\officecli\\McpInstaller.cs", "source_location": "L37"}, {"caller_nid": "mcpinstaller_mcpinstaller_install", "callee": "WriteLine", "source_file": "D:\\Excel Add-in V2\\sources\\OfficeCLI-main\\OfficeCLI-main\\src\\officecli\\McpInstaller.cs", "source_location": "L40"}, {"caller_nid": "mcpinstaller_mcpinstaller_install", "callee": "WriteLine", "source_file": "D:\\Excel Add-in V2\\sources\\OfficeCLI-main\\OfficeCLI-main\\src\\officecli\\McpInstaller.cs", "source_location": "L41"}, {"caller_nid": "mcpinstaller_mcpinstaller_install", "callee": "WriteLine", "source_file": "D:\\Excel Add-in V2\\sources\\OfficeCLI-main\\OfficeCLI-main\\src\\officecli\\McpInstaller.cs", "source_location": "L42"}, {"caller_nid": "mcpinstaller_mcpinstaller_uninstall", "callee": "ToLowerInvariant", "source_file": "D:\\Excel Add-in V2\\sources\\OfficeCLI-main\\OfficeCLI-main\\src\\officecli\\McpInstaller.cs", "source_location": "L49"}, {"caller_nid": "mcpinstaller_mcpinstaller_uninstall", "callee": "WriteLine", "source_file": "D:\\Excel Add-in V2\\sources\\OfficeCLI-main\\OfficeCLI-main\\src\\officecli\\McpInstaller.cs", "source_location": "L64"}, {"caller_nid": "mcpinstaller_mcpinstaller_installlmstudio", "callee": "Combine", "source_file": "D:\\Excel Add-in V2\\sources\\OfficeCLI-main\\OfficeCLI-main\\src\\officecli\\McpInstaller.cs", "source_location": "L73"}, {"caller_nid": "mcpinstaller_mcpinstaller_installlmstudio", "callee": "GetFolderPath", "source_file": "D:\\Excel Add-in V2\\sources\\OfficeCLI-main\\OfficeCLI-main\\src\\officecli\\McpInstaller.cs", "source_location": "L74"}, {"caller_nid": "mcpinstaller_mcpinstaller_installlmstudio", "callee": "CreateDirectory", "source_file": "D:\\Excel Add-in V2\\sources\\OfficeCLI-main\\OfficeCLI-main\\src\\officecli\\McpInstaller.cs", "source_location": "L77"}, {"caller_nid": "mcpinstaller_mcpinstaller_installlmstudio", "callee": "WriteAllText", "source_file": "D:\\Excel Add-in V2\\sources\\OfficeCLI-main\\OfficeCLI-main\\src\\officecli\\McpInstaller.cs", "source_location": "L79"}, {"caller_nid": "mcpinstaller_mcpinstaller_installlmstudio", "callee": "Combine", "source_file": "D:\\Excel Add-in V2\\sources\\OfficeCLI-main\\OfficeCLI-main\\src\\officecli\\McpInstaller.cs", "source_location": "L79"}, {"caller_nid": "mcpinstaller_mcpinstaller_installlmstudio", "callee": "WriteAllText", "source_file": "D:\\Excel Add-in V2\\sources\\OfficeCLI-main\\OfficeCLI-main\\src\\officecli\\McpInstaller.cs", "source_location": "L82"}, {"caller_nid": "mcpinstaller_mcpinstaller_installlmstudio", "callee": "Combine", "source_file": "D:\\Excel Add-in V2\\sources\\OfficeCLI-main\\OfficeCLI-main\\src\\officecli\\McpInstaller.cs", "source_location": "L82"}, {"caller_nid": "mcpinstaller_mcpinstaller_installlmstudio", "callee": "ToUnixTimeMilliseconds", "source_file": "D:\\Excel Add-in V2\\sources\\OfficeCLI-main\\OfficeCLI-main\\src\\officecli\\McpInstaller.cs", "source_location": "L85"}, {"caller_nid": "mcpinstaller_mcpinstaller_installlmstudio", "callee": "WriteAllText", "source_file": "D:\\Excel Add-in V2\\sources\\OfficeCLI-main\\OfficeCLI-main\\src\\officecli\\McpInstaller.cs", "source_location": "L86"}, {"caller_nid": "mcpinstaller_mcpinstaller_installlmstudio", "callee": "Combine", "source_file": "D:\\Excel Add-in V2\\sources\\OfficeCLI-main\\OfficeCLI-main\\src\\officecli\\McpInstaller.cs", "source_location": "L86"}, {"caller_nid": "mcpinstaller_mcpinstaller_installlmstudio", "callee": "WriteLine", "source_file": "D:\\Excel Add-in V2\\sources\\OfficeCLI-main\\OfficeCLI-main\\src\\officecli\\McpInstaller.cs", "source_location": "L89"}, {"caller_nid": "mcpinstaller_mcpinstaller_installlmstudio", "callee": "WriteLine", "source_file": "D:\\Excel Add-in V2\\sources\\OfficeCLI-main\\OfficeCLI-main\\src\\officecli\\McpInstaller.cs", "source_location": "L90"}, {"caller_nid": "mcpinstaller_mcpinstaller_installlmstudio", "callee": "WriteLine", "source_file": "D:\\Excel Add-in V2\\sources\\OfficeCLI-main\\OfficeCLI-main\\src\\officecli\\McpInstaller.cs", "source_location": "L91"}, {"caller_nid": "mcpinstaller_mcpinstaller_uninstalllmstudio", "callee": "Combine", "source_file": "D:\\Excel Add-in V2\\sources\\OfficeCLI-main\\OfficeCLI-main\\src\\officecli\\McpInstaller.cs", "source_location": "L96"}, {"caller_nid": "mcpinstaller_mcpinstaller_uninstalllmstudio", "callee": "GetFolderPath", "source_file": "D:\\Excel Add-in V2\\sources\\OfficeCLI-main\\OfficeCLI-main\\src\\officecli\\McpInstaller.cs", "source_location": "L97"}, {"caller_nid": "mcpinstaller_mcpinstaller_uninstalllmstudio", "callee": "Exists", "source_file": "D:\\Excel Add-in V2\\sources\\OfficeCLI-main\\OfficeCLI-main\\src\\officecli\\McpInstaller.cs", "source_location": "L99"}, {"caller_nid": "mcpinstaller_mcpinstaller_uninstalllmstudio", "callee": "Delete", "source_file": "D:\\Excel Add-in V2\\sources\\OfficeCLI-main\\OfficeCLI-main\\src\\officecli\\McpInstaller.cs", "source_location": "L101"}, {"caller_nid": "mcpinstaller_mcpinstaller_uninstalllmstudio", "callee": "WriteLine", "source_file": "D:\\Excel Add-in V2\\sources\\OfficeCLI-main\\OfficeCLI-main\\src\\officecli\\McpInstaller.cs", "source_location": "L102"}, {"caller_nid": "mcpinstaller_mcpinstaller_uninstalllmstudio", "callee": "WriteLine", "source_file": "D:\\Excel Add-in V2\\sources\\OfficeCLI-main\\OfficeCLI-main\\src\\officecli\\McpInstaller.cs", "source_location": "L106"}, {"caller_nid": "mcpinstaller_mcpinstaller_getclaudesettingspath", "callee": "Combine", "source_file": "D:\\Excel Add-in V2\\sources\\OfficeCLI-main\\OfficeCLI-main\\src\\officecli\\McpInstaller.cs", "source_location": "L113"}, {"caller_nid": "mcpinstaller_mcpinstaller_getclaudesettingspath", "callee": "GetFolderPath", "source_file": "D:\\Excel Add-in V2\\sources\\OfficeCLI-main\\OfficeCLI-main\\src\\officecli\\McpInstaller.cs", "source_location": "L113"}, {"caller_nid": "mcpinstaller_mcpinstaller_getcursormcppath", "callee": "Combine", "source_file": "D:\\Excel Add-in V2\\sources\\OfficeCLI-main\\OfficeCLI-main\\src\\officecli\\McpInstaller.cs", "source_location": "L121"}, {"caller_nid": "mcpinstaller_mcpinstaller_getcursormcppath", "callee": "GetFolderPath", "source_file": "D:\\Excel Add-in V2\\sources\\OfficeCLI-main\\OfficeCLI-main\\src\\officecli\\McpInstaller.cs", "source_location": "L121"}, {"caller_nid": "mcpinstaller_mcpinstaller_getvscodemcppath", "callee": "Combine", "source_file": "D:\\Excel Add-in V2\\sources\\OfficeCLI-main\\OfficeCLI-main\\src\\officecli\\McpInstaller.cs", "source_location": "L129"}, {"caller_nid": "mcpinstaller_mcpinstaller_getvscodemcppath", "callee": "GetFolderPath", "source_file": "D:\\Excel Add-in V2\\sources\\OfficeCLI-main\\OfficeCLI-main\\src\\officecli\\McpInstaller.cs", "source_location": "L129"}, {"caller_nid": "mcpinstaller_mcpinstaller_installjson", "callee": "GetDirectoryName", "source_file": "D:\\Excel Add-in V2\\sources\\OfficeCLI-main\\OfficeCLI-main\\src\\officecli\\McpInstaller.cs", "source_location": "L138"}, {"caller_nid": "mcpinstaller_mcpinstaller_installjson", "callee": "CreateDirectory", "source_file": "D:\\Excel Add-in V2\\sources\\OfficeCLI-main\\OfficeCLI-main\\src\\officecli\\McpInstaller.cs", "source_location": "L139"}, {"caller_nid": "mcpinstaller_mcpinstaller_installjson", "callee": "Exists", "source_file": "D:\\Excel Add-in V2\\sources\\OfficeCLI-main\\OfficeCLI-main\\src\\officecli\\McpInstaller.cs", "source_location": "L142"}, {"caller_nid": "mcpinstaller_mcpinstaller_installjson", "callee": "Parse", "source_file": "D:\\Excel Add-in V2\\sources\\OfficeCLI-main\\OfficeCLI-main\\src\\officecli\\McpInstaller.cs", "source_location": "L146"}, {"caller_nid": "mcpinstaller_mcpinstaller_installjson", "callee": "ReadAllText", "source_file": "D:\\Excel Add-in V2\\sources\\OfficeCLI-main\\OfficeCLI-main\\src\\officecli\\McpInstaller.cs", "source_location": "L146"}, {"caller_nid": "mcpinstaller_mcpinstaller_installjson", "callee": "EnumerateObject", "source_file": "D:\\Excel Add-in V2\\sources\\OfficeCLI-main\\OfficeCLI-main\\src\\officecli\\McpInstaller.cs", "source_location": "L147"}, {"caller_nid": "mcpinstaller_mcpinstaller_installjson", "callee": "Clone", "source_file": "D:\\Excel Add-in V2\\sources\\OfficeCLI-main\\OfficeCLI-main\\src\\officecli\\McpInstaller.cs", "source_location": "L148"}, {"caller_nid": "mcpinstaller_mcpinstaller_installjson", "callee": "TryGetValue", "source_file": "D:\\Excel Add-in V2\\sources\\OfficeCLI-main\\OfficeCLI-main\\src\\officecli\\McpInstaller.cs", "source_location": "L155"}, {"caller_nid": "mcpinstaller_mcpinstaller_installjson", "callee": "EnumerateObject", "source_file": "D:\\Excel Add-in V2\\sources\\OfficeCLI-main\\OfficeCLI-main\\src\\officecli\\McpInstaller.cs", "source_location": "L157"}, {"caller_nid": "mcpinstaller_mcpinstaller_installjson", "callee": "WriteStartObject", "source_file": "D:\\Excel Add-in V2\\sources\\OfficeCLI-main\\OfficeCLI-main\\src\\officecli\\McpInstaller.cs", "source_location": "L171"}, {"caller_nid": "mcpinstaller_mcpinstaller_installjson", "callee": "WritePropertyName", "source_file": "D:\\Excel Add-in V2\\sources\\OfficeCLI-main\\OfficeCLI-main\\src\\officecli\\McpInstaller.cs", "source_location": "L174"}, {"caller_nid": "mcpinstaller_mcpinstaller_installjson", "callee": "WriteTo", "source_file": "D:\\Excel Add-in V2\\sources\\OfficeCLI-main\\OfficeCLI-main\\src\\officecli\\McpInstaller.cs", "source_location": "L176"}, {"caller_nid": "mcpinstaller_mcpinstaller_installjson", "callee": "WriteNullValue", "source_file": "D:\\Excel Add-in V2\\sources\\OfficeCLI-main\\OfficeCLI-main\\src\\officecli\\McpInstaller.cs", "source_location": "L180"}, {"caller_nid": "mcpinstaller_mcpinstaller_installjson", "callee": "WriteEndObject", "source_file": "D:\\Excel Add-in V2\\sources\\OfficeCLI-main\\OfficeCLI-main\\src\\officecli\\McpInstaller.cs", "source_location": "L182"}, {"caller_nid": "mcpinstaller_mcpinstaller_installjson", "callee": "WriteAllText", "source_file": "D:\\Excel Add-in V2\\sources\\OfficeCLI-main\\OfficeCLI-main\\src\\officecli\\McpInstaller.cs", "source_location": "L185"}, {"caller_nid": "mcpinstaller_mcpinstaller_installjson", "callee": "GetString", "source_file": "D:\\Excel Add-in V2\\sources\\OfficeCLI-main\\OfficeCLI-main\\src\\officecli\\McpInstaller.cs", "source_location": "L185"}, {"caller_nid": "mcpinstaller_mcpinstaller_installjson", "callee": "ToArray", "source_file": "D:\\Excel Add-in V2\\sources\\OfficeCLI-main\\OfficeCLI-main\\src\\officecli\\McpInstaller.cs", "source_location": "L185"}, {"caller_nid": "mcpinstaller_mcpinstaller_installjson", "callee": "WriteLine", "source_file": "D:\\Excel Add-in V2\\sources\\OfficeCLI-main\\OfficeCLI-main\\src\\officecli\\McpInstaller.cs", "source_location": "L187"}, {"caller_nid": "mcpinstaller_mcpinstaller_installjson", "callee": "WriteLine", "source_file": "D:\\Excel Add-in V2\\sources\\OfficeCLI-main\\OfficeCLI-main\\src\\officecli\\McpInstaller.cs", "source_location": "L188"}, {"caller_nid": "mcpinstaller_mcpinstaller_writeserversdict", "callee": "WriteStartObject", "source_file": "D:\\Excel Add-in V2\\sources\\OfficeCLI-main\\OfficeCLI-main\\src\\officecli\\McpInstaller.cs", "source_location": "L193"}, {"caller_nid": "mcpinstaller_mcpinstaller_writeserversdict", "callee": "WritePropertyName", "source_file": "D:\\Excel Add-in V2\\sources\\OfficeCLI-main\\OfficeCLI-main\\src\\officecli\\McpInstaller.cs", "source_location": "L196"}, {"caller_nid": "mcpinstaller_mcpinstaller_writeserversdict", "callee": "WriteTo", "source_file": "D:\\Excel Add-in V2\\sources\\OfficeCLI-main\\OfficeCLI-main\\src\\officecli\\McpInstaller.cs", "source_location": "L198"}, {"caller_nid": "mcpinstaller_mcpinstaller_writeserversdict", "callee": "WriteStartObject", "source_file": "D:\\Excel Add-in V2\\sources\\OfficeCLI-main\\OfficeCLI-main\\src\\officecli\\McpInstaller.cs", "source_location": "L201"}, {"caller_nid": "mcpinstaller_mcpinstaller_writeserversdict", "callee": "WriteString", "source_file": "D:\\Excel Add-in V2\\sources\\OfficeCLI-main\\OfficeCLI-main\\src\\officecli\\McpInstaller.cs", "source_location": "L202"}, {"caller_nid": "mcpinstaller_mcpinstaller_writeserversdict", "callee": "WriteStartArray", "source_file": "D:\\Excel Add-in V2\\sources\\OfficeCLI-main\\OfficeCLI-main\\src\\officecli\\McpInstaller.cs", "source_location": "L203"}, {"caller_nid": "mcpinstaller_mcpinstaller_writeserversdict", "callee": "WriteStringValue", "source_file": "D:\\Excel Add-in V2\\sources\\OfficeCLI-main\\OfficeCLI-main\\src\\officecli\\McpInstaller.cs", "source_location": "L204"}, {"caller_nid": "mcpinstaller_mcpinstaller_writeserversdict", "callee": "WriteEndArray", "source_file": "D:\\Excel Add-in V2\\sources\\OfficeCLI-main\\OfficeCLI-main\\src\\officecli\\McpInstaller.cs", "source_location": "L205"}, {"caller_nid": "mcpinstaller_mcpinstaller_writeserversdict", "callee": "WriteEndObject", "source_file": "D:\\Excel Add-in V2\\sources\\OfficeCLI-main\\OfficeCLI-main\\src\\officecli\\McpInstaller.cs", "source_location": "L206"}, {"caller_nid": "mcpinstaller_mcpinstaller_writeserversdict", "callee": "WriteEndObject", "source_file": "D:\\Excel Add-in V2\\sources\\OfficeCLI-main\\OfficeCLI-main\\src\\officecli\\McpInstaller.cs", "source_location": "L209"}, {"caller_nid": "mcpinstaller_mcpinstaller_uninstalljson", "callee": "Exists", "source_file": "D:\\Excel Add-in V2\\sources\\OfficeCLI-main\\OfficeCLI-main\\src\\officecli\\McpInstaller.cs", "source_location": "L214"}, {"caller_nid": "mcpinstaller_mcpinstaller_uninstalljson", "callee": "WriteLine", "source_file": "D:\\Excel Add-in V2\\sources\\OfficeCLI-main\\OfficeCLI-main\\src\\officecli\\McpInstaller.cs", "source_location": "L216"}, {"caller_nid": "mcpinstaller_mcpinstaller_uninstalljson", "callee": "Parse", "source_file": "D:\\Excel Add-in V2\\sources\\OfficeCLI-main\\OfficeCLI-main\\src\\officecli\\McpInstaller.cs", "source_location": "L222"}, {"caller_nid": "mcpinstaller_mcpinstaller_uninstalljson", "callee": "ReadAllText", "source_file": "D:\\Excel Add-in V2\\sources\\OfficeCLI-main\\OfficeCLI-main\\src\\officecli\\McpInstaller.cs", "source_location": "L222"}, {"caller_nid": "mcpinstaller_mcpinstaller_uninstalljson", "callee": "WriteStartObject", "source_file": "D:\\Excel Add-in V2\\sources\\OfficeCLI-main\\OfficeCLI-main\\src\\officecli\\McpInstaller.cs", "source_location": "L226"}, {"caller_nid": "mcpinstaller_mcpinstaller_uninstalljson", "callee": "EnumerateObject", "source_file": "D:\\Excel Add-in V2\\sources\\OfficeCLI-main\\OfficeCLI-main\\src\\officecli\\McpInstaller.cs", "source_location": "L227"}, {"caller_nid": "mcpinstaller_mcpinstaller_uninstalljson", "callee": "WriteStartObject", "source_file": "D:\\Excel Add-in V2\\sources\\OfficeCLI-main\\OfficeCLI-main\\src\\officecli\\McpInstaller.cs", "source_location": "L231"}, {"caller_nid": "mcpinstaller_mcpinstaller_uninstalljson", "callee": "EnumerateObject", "source_file": "D:\\Excel Add-in V2\\sources\\OfficeCLI-main\\OfficeCLI-main\\src\\officecli\\McpInstaller.cs", "source_location": "L232"}, {"caller_nid": "mcpinstaller_mcpinstaller_uninstalljson", "callee": "WritePropertyName", "source_file": "D:\\Excel Add-in V2\\sources\\OfficeCLI-main\\OfficeCLI-main\\src\\officecli\\McpInstaller.cs", "source_location": "L236"}, {"caller_nid": "mcpinstaller_mcpinstaller_uninstalljson", "callee": "WriteTo", "source_file": "D:\\Excel Add-in V2\\sources\\OfficeCLI-main\\OfficeCLI-main\\src\\officecli\\McpInstaller.cs", "source_location": "L237"}, {"caller_nid": "mcpinstaller_mcpinstaller_uninstalljson", "callee": "WriteEndObject", "source_file": "D:\\Excel Add-in V2\\sources\\OfficeCLI-main\\OfficeCLI-main\\src\\officecli\\McpInstaller.cs", "source_location": "L240"}, {"caller_nid": "mcpinstaller_mcpinstaller_uninstalljson", "callee": "WritePropertyName", "source_file": "D:\\Excel Add-in V2\\sources\\OfficeCLI-main\\OfficeCLI-main\\src\\officecli\\McpInstaller.cs", "source_location": "L244"}, {"caller_nid": "mcpinstaller_mcpinstaller_uninstalljson", "callee": "WriteTo", "source_file": "D:\\Excel Add-in V2\\sources\\OfficeCLI-main\\OfficeCLI-main\\src\\officecli\\McpInstaller.cs", "source_location": "L245"}, {"caller_nid": "mcpinstaller_mcpinstaller_uninstalljson", "callee": "WriteEndObject", "source_file": "D:\\Excel Add-in V2\\sources\\OfficeCLI-main\\OfficeCLI-main\\src\\officecli\\McpInstaller.cs", "source_location": "L248"}, {"caller_nid": "mcpinstaller_mcpinstaller_uninstalljson", "callee": "WriteAllText", "source_file": "D:\\Excel Add-in V2\\sources\\OfficeCLI-main\\OfficeCLI-main\\src\\officecli\\McpInstaller.cs", "source_location": "L250"}, {"caller_nid": "mcpinstaller_mcpinstaller_uninstalljson", "callee": "GetString", "source_file": "D:\\Excel Add-in V2\\sources\\OfficeCLI-main\\OfficeCLI-main\\src\\officecli\\McpInstaller.cs", "source_location": "L250"}, {"caller_nid": "mcpinstaller_mcpinstaller_uninstalljson", "callee": "ToArray", "source_file": "D:\\Excel Add-in V2\\sources\\OfficeCLI-main\\OfficeCLI-main\\src\\officecli\\McpInstaller.cs", "source_location": "L250"}, {"caller_nid": "mcpinstaller_mcpinstaller_uninstalljson", "callee": "WriteLine", "source_file": "D:\\Excel Add-in V2\\sources\\OfficeCLI-main\\OfficeCLI-main\\src\\officecli\\McpInstaller.cs", "source_location": "L251"}, {"caller_nid": "mcpinstaller_mcpinstaller_uninstalljson", "callee": "WriteLine", "source_file": "D:\\Excel Add-in V2\\sources\\OfficeCLI-main\\OfficeCLI-main\\src\\officecli\\McpInstaller.cs", "source_location": "L255"}, {"caller_nid": "mcpinstaller_mcpinstaller_liststatus", "callee": "WriteLine", "source_file": "D:\\Excel Add-in V2\\sources\\OfficeCLI-main\\OfficeCLI-main\\src\\officecli\\McpInstaller.cs", "source_location": "L263"}, {"caller_nid": "mcpinstaller_mcpinstaller_liststatus", "callee": "WriteLine", "source_file": "D:\\Excel Add-in V2\\sources\\OfficeCLI-main\\OfficeCLI-main\\src\\officecli\\McpInstaller.cs", "source_location": "L264"}, {"caller_nid": "mcpinstaller_mcpinstaller_liststatus", "callee": "Combine", "source_file": "D:\\Excel Add-in V2\\sources\\OfficeCLI-main\\OfficeCLI-main\\src\\officecli\\McpInstaller.cs", "source_location": "L266"}, {"caller_nid": "mcpinstaller_mcpinstaller_liststatus", "callee": "GetFolderPath", "source_file": "D:\\Excel Add-in V2\\sources\\OfficeCLI-main\\OfficeCLI-main\\src\\officecli\\McpInstaller.cs", "source_location": "L267"}, {"caller_nid": "mcpinstaller_mcpinstaller_liststatus", "callee": "WriteLine", "source_file": "D:\\Excel Add-in V2\\sources\\OfficeCLI-main\\OfficeCLI-main\\src\\officecli\\McpInstaller.cs", "source_location": "L273"}, {"caller_nid": "mcpinstaller_mcpinstaller_liststatus", "callee": "WriteLine", "source_file": "D:\\Excel Add-in V2\\sources\\OfficeCLI-main\\OfficeCLI-main\\src\\officecli\\McpInstaller.cs", "source_location": "L274"}, {"caller_nid": "mcpinstaller_mcpinstaller_liststatus", "callee": "WriteLine", "source_file": "D:\\Excel Add-in V2\\sources\\OfficeCLI-main\\OfficeCLI-main\\src\\officecli\\McpInstaller.cs", "source_location": "L275"}, {"caller_nid": "mcpinstaller_mcpinstaller_liststatus", "callee": "WriteLine", "source_file": "D:\\Excel Add-in V2\\sources\\OfficeCLI-main\\OfficeCLI-main\\src\\officecli\\McpInstaller.cs", "source_location": "L276"}, {"caller_nid": "mcpinstaller_mcpinstaller_checkstatus", "callee": "Exists", "source_file": "D:\\Excel Add-in V2\\sources\\OfficeCLI-main\\OfficeCLI-main\\src\\officecli\\McpInstaller.cs", "source_location": "L281"}, {"caller_nid": "mcpinstaller_mcpinstaller_checkstatus", "callee": "WriteLine", "source_file": "D:\\Excel Add-in V2\\sources\\OfficeCLI-main\\OfficeCLI-main\\src\\officecli\\McpInstaller.cs", "source_location": "L282"}, {"caller_nid": "mcpinstaller_mcpinstaller_checkjsonstatus", "callee": "Exists", "source_file": "D:\\Excel Add-in V2\\sources\\OfficeCLI-main\\OfficeCLI-main\\src\\officecli\\McpInstaller.cs", "source_location": "L288"}, {"caller_nid": "mcpinstaller_mcpinstaller_checkjsonstatus", "callee": "Parse", "source_file": "D:\\Excel Add-in V2\\sources\\OfficeCLI-main\\OfficeCLI-main\\src\\officecli\\McpInstaller.cs", "source_location": "L292"}, {"caller_nid": "mcpinstaller_mcpinstaller_checkjsonstatus", "callee": "ReadAllText", "source_file": "D:\\Excel Add-in V2\\sources\\OfficeCLI-main\\OfficeCLI-main\\src\\officecli\\McpInstaller.cs", "source_location": "L292"}, {"caller_nid": "mcpinstaller_mcpinstaller_checkjsonstatus", "callee": "TryGetProperty", "source_file": "D:\\Excel Add-in V2\\sources\\OfficeCLI-main\\OfficeCLI-main\\src\\officecli\\McpInstaller.cs", "source_location": "L293"}, {"caller_nid": "mcpinstaller_mcpinstaller_checkjsonstatus", "callee": "TryGetProperty", "source_file": "D:\\Excel Add-in V2\\sources\\OfficeCLI-main\\OfficeCLI-main\\src\\officecli\\McpInstaller.cs", "source_location": "L294"}, {"caller_nid": "mcpinstaller_mcpinstaller_checkjsonstatus", "callee": "WriteLine", "source_file": "D:\\Excel Add-in V2\\sources\\OfficeCLI-main\\OfficeCLI-main\\src\\officecli\\McpInstaller.cs", "source_location": "L298"}, {"caller_nid": "mcpinstaller_mcpinstaller_escapejson", "callee": "Replace", "source_file": "D:\\Excel Add-in V2\\sources\\OfficeCLI-main\\OfficeCLI-main\\src\\officecli\\McpInstaller.cs", "source_location": "L301"}, {"caller_nid": "mcpinstaller_mcpinstaller_escapejson", "callee": "Replace", "source_file": "D:\\Excel Add-in V2\\sources\\OfficeCLI-main\\OfficeCLI-main\\src\\officecli\\McpInstaller.cs", "source_location": "L301"}]}