{"nodes": [{"id": "d_excel_add_in_v2_sources_mcp_server_excel_main_mcp_server_excel_main_src_excelmcp_generators_shared_models_cs", "label": "Models.cs", "file_type": "code", "source_file": "D:\\Excel Add-in V2\\sources\\mcp-server-excel-main\\mcp-server-excel-main\\src\\ExcelMcp.Generators.Shared\\Models.cs", "source_location": "L1"}, {"id": "models_serviceinfo", "label": "ServiceInfo", "file_type": "code", "source_file": "D:\\Excel Add-in V2\\sources\\mcp-server-excel-main\\mcp-server-excel-main\\src\\ExcelMcp.Generators.Shared\\Models.cs", "source_location": "L6"}, {"id": "models_methodinfo", "label": "MethodInfo", "file_type": "code", "source_file": "D:\\Excel Add-in V2\\sources\\mcp-server-excel-main\\mcp-server-excel-main\\src\\ExcelMcp.Generators.Shared\\Models.cs", "source_location": "L51"}, {"id": "models_parameterinfo", "label": "ParameterInfo", "file_type": "code", "source_file": "D:\\Excel Add-in V2\\sources\\mcp-server-excel-main\\mcp-server-excel-main\\src\\ExcelMcp.Generators.Shared\\Models.cs", "source_location": "L83"}, {"id": "models_exposedparameter", "label": "ExposedParameter", "file_type": "code", "source_file": "D:\\Excel Add-in V2\\sources\\mcp-server-excel-main\\mcp-server-excel-main\\src\\ExcelMcp.Generators.Shared\\Models.cs", "source_location": "L127"}], "edges": [{"source": "d_excel_add_in_v2_sources_mcp_server_excel_main_mcp_server_excel_main_src_excelmcp_generators_shared_models_cs", "target": "models_serviceinfo", "relation": "contains", "confidence": "EXTRACTED", "source_file": "D:\\Excel Add-in V2\\sources\\mcp-server-excel-main\\mcp-server-excel-main\\src\\ExcelMcp.Generators.Shared\\Models.cs", "source_location": "L6", "weight": 1.0}, {"source": "d_excel_add_in_v2_sources_mcp_server_excel_main_mcp_server_excel_main_src_excelmcp_generators_shared_models_cs", "target": "models_methodinfo", "relation": "contains", "confidence": "EXTRACTED", "source_file": "D:\\Excel Add-in V2\\sources\\mcp-server-excel-main\\mcp-server-excel-main\\src\\ExcelMcp.Generators.Shared\\Models.cs", "source_location": "L51", "weight": 1.0}, {"source": "d_excel_add_in_v2_sources_mcp_server_excel_main_mcp_server_excel_main_src_excelmcp_generators_shared_models_cs", "target": "models_parameterinfo", "relation": "contains", "confidence": "EXTRACTED", "source_file": "D:\\Excel Add-in V2\\sources\\mcp-server-excel-main\\mcp-server-excel-main\\src\\ExcelMcp.Generators.Shared\\Models.cs", "source_location": "L83", "weight": 1.0}, {"source": "d_excel_add_in_v2_sources_mcp_server_excel_main_mcp_server_excel_main_src_excelmcp_generators_shared_models_cs", "target": "models_exposedparameter", "relation": "contains", "confidence": "EXTRACTED", "source_file": "D:\\Excel Add-in V2\\sources\\mcp-server-excel-main\\mcp-server-excel-main\\src\\ExcelMcp.Generators.Shared\\Models.cs", "source_location": "L127", "weight": 1.0}], "raw_calls": []}