{"nodes": [{"id": "d_excel_add_in_v2_sources_officecli_main_officecli_main_src_officecli_wikihelploader_cs", "label": "WikiHelpLoader.cs", "file_type": "code", "source_file": "D:\\Excel Add-in V2\\sources\\OfficeCLI-main\\OfficeCLI-main\\src\\officecli\\WikiHelpLoader.cs", "source_location": "L1"}, {"id": "wikihelploader_wikihelploader", "label": "WikiHelpLoader", "file_type": "code", "source_file": "D:\\Excel Add-in V2\\sources\\OfficeCLI-main\\OfficeCLI-main\\src\\officecli\\WikiHelpLoader.cs", "source_location": "L18"}, {"id": "wikihelploader_wikihelploader_trygethelp", "label": ".TryGetHelp()", "file_type": "code", "source_file": "D:\\Excel Add-in V2\\sources\\OfficeCLI-main\\OfficeCLI-main\\src\\officecli\\WikiHelpLoader.cs", "source_location": "L51"}, {"id": "wikihelploader_wikihelploader_tryloadlayer1", "label": ".TryLoadLayer1()", "file_type": "code", "source_file": "D:\\Excel Add-in V2\\sources\\OfficeCLI-main\\OfficeCLI-main\\src\\officecli\\WikiHelpLoader.cs", "source_location": "L84"}, {"id": "wikihelploader_wikihelploader_extractpropertysection", "label": ".ExtractPropertySection()", "file_type": "code", "source_file": "D:\\Excel Add-in V2\\sources\\OfficeCLI-main\\OfficeCLI-main\\src\\officecli\\WikiHelpLoader.cs", "source_location": "L125"}, {"id": "wikihelploader_wikihelploader_tryloadandrender", "label": ".TryLoadAndRender()", "file_type": "code", "source_file": "D:\\Excel Add-in V2\\sources\\OfficeCLI-main\\OfficeCLI-main\\src\\officecli\\WikiHelpLoader.cs", "source_location": "L201"}, {"id": "wikihelploader_wikihelploader_tryloadfromlocalwiki", "label": ".TryLoadFromLocalWiki()", "file_type": "code", "source_file": "D:\\Excel Add-in V2\\sources\\OfficeCLI-main\\OfficeCLI-main\\src\\officecli\\WikiHelpLoader.cs", "source_location": "L216"}, {"id": "wikihelploader_wikihelploader_tryloadfromembeddedresource", "label": ".TryLoadFromEmbeddedResource()", "file_type": "code", "source_file": "D:\\Excel Add-in V2\\sources\\OfficeCLI-main\\OfficeCLI-main\\src\\officecli\\WikiHelpLoader.cs", "source_location": "L224"}, {"id": "wikihelploader_wikihelploader_findlocalwikidir", "label": ".FindLocalWikiDir()", "file_type": "code", "source_file": "D:\\Excel Add-in V2\\sources\\OfficeCLI-main\\OfficeCLI-main\\src\\officecli\\WikiHelpLoader.cs", "source_location": "L247"}, {"id": "wikihelploader_wikihelploader_findwikifiles", "label": ".FindWikiFiles()", "file_type": "code", "source_file": "D:\\Excel Add-in V2\\sources\\OfficeCLI-main\\OfficeCLI-main\\src\\officecli\\WikiHelpLoader.cs", "source_location": "L283"}, {"id": "wikihelploader_wikihelploader_rendermarkdown", "label": ".RenderMarkdown()", "file_type": "code", "source_file": "D:\\Excel Add-in V2\\sources\\OfficeCLI-main\\OfficeCLI-main\\src\\officecli\\WikiHelpLoader.cs", "source_location": "L331"}], "edges": [{"source": "d_excel_add_in_v2_sources_officecli_main_officecli_main_src_officecli_wikihelploader_cs", "target": "reflection", "relation": "imports", "confidence": "EXTRACTED", "source_file": "D:\\Excel Add-in V2\\sources\\OfficeCLI-main\\OfficeCLI-main\\src\\officecli\\WikiHelpLoader.cs", "source_location": "L4", "weight": 1.0}, {"source": "d_excel_add_in_v2_sources_officecli_main_officecli_main_src_officecli_wikihelploader_cs", "target": "regularexpressions", "relation": "imports", "confidence": "EXTRACTED", "source_file": "D:\\Excel Add-in V2\\sources\\OfficeCLI-main\\OfficeCLI-main\\src\\officecli\\WikiHelpLoader.cs", "source_location": "L5", "weight": 1.0}, {"source": "d_excel_add_in_v2_sources_officecli_main_officecli_main_src_officecli_wikihelploader_cs", "target": "wikihelploader_wikihelploader", "relation": "contains", "confidence": "EXTRACTED", "source_file": "D:\\Excel Add-in V2\\sources\\OfficeCLI-main\\OfficeCLI-main\\src\\officecli\\WikiHelpLoader.cs", "source_location": "L18", "weight": 1.0}, {"source": "wikihelploader_wikihelploader", "target": "wikihelploader_wikihelploader_trygethelp", "relation": "method", "confidence": "EXTRACTED", "source_file": "D:\\Excel Add-in V2\\sources\\OfficeCLI-main\\OfficeCLI-main\\src\\officecli\\WikiHelpLoader.cs", "source_location": "L51", "weight": 1.0}, {"source": "wikihelploader_wikihelploader", "target": "wikihelploader_wikihelploader_tryloadlayer1", "relation": "method", "confidence": "EXTRACTED", "source_file": "D:\\Excel Add-in V2\\sources\\OfficeCLI-main\\OfficeCLI-main\\src\\officecli\\WikiHelpLoader.cs", "source_location": "L84", "weight": 1.0}, {"source": "wikihelploader_wikihelploader", "target": "wikihelploader_wikihelploader_extractpropertysection", "relation": "method", "confidence": "EXTRACTED", "source_file": "D:\\Excel Add-in V2\\sources\\OfficeCLI-main\\OfficeCLI-main\\src\\officecli\\WikiHelpLoader.cs", "source_location": "L125", "weight": 1.0}, {"source": "wikihelploader_wikihelploader", "target": "wikihelploader_wikihelploader_tryloadandrender", "relation": "method", "confidence": "EXTRACTED", "source_file": "D:\\Excel Add-in V2\\sources\\OfficeCLI-main\\OfficeCLI-main\\src\\officecli\\WikiHelpLoader.cs", "source_location": "L201", "weight": 1.0}, {"source": "wikihelploader_wikihelploader", "target": "wikihelploader_wikihelploader_tryloadfromlocalwiki", "relation": "method", "confidence": "EXTRACTED", "source_file": "D:\\Excel Add-in V2\\sources\\OfficeCLI-main\\OfficeCLI-main\\src\\officecli\\WikiHelpLoader.cs", "source_location": "L216", "weight": 1.0}, {"source": "wikihelploader_wikihelploader", "target": "wikihelploader_wikihelploader_tryloadfromembeddedresource", "relation": "method", "confidence": "EXTRACTED", "source_file": "D:\\Excel Add-in V2\\sources\\OfficeCLI-main\\OfficeCLI-main\\src\\officecli\\WikiHelpLoader.cs", "source_location": "L224", "weight": 1.0}, {"source": "wikihelploader_wikihelploader", "target": "wikihelploader_wikihelploader_findlocalwikidir", "relation": "method", "confidence": "EXTRACTED", "source_file": "D:\\Excel Add-in V2\\sources\\OfficeCLI-main\\OfficeCLI-main\\src\\officecli\\WikiHelpLoader.cs", "source_location": "L247", "weight": 1.0}, {"source": "wikihelploader_wikihelploader", "target": "wikihelploader_wikihelploader_findwikifiles", "relation": "method", "confidence": "EXTRACTED", "source_file": "D:\\Excel Add-in V2\\sources\\OfficeCLI-main\\OfficeCLI-main\\src\\officecli\\WikiHelpLoader.cs", "source_location": "L283", "weight": 1.0}, {"source": "wikihelploader_wikihelploader", "target": "wikihelploader_wikihelploader_rendermarkdown", "relation": "method", "confidence": "EXTRACTED", "source_file": "D:\\Excel Add-in V2\\sources\\OfficeCLI-main\\OfficeCLI-main\\src\\officecli\\WikiHelpLoader.cs", "source_location": "L331", "weight": 1.0}, {"source": "wikihelploader_wikihelploader_trygethelp", "target": "wikihelploader_wikihelploader_tryloadandrender", "relation": "calls", "confidence": "EXTRACTED", "source_file": "D:\\Excel Add-in V2\\sources\\OfficeCLI-main\\OfficeCLI-main\\src\\officecli\\WikiHelpLoader.cs", "source_location": "L56", "weight": 1.0}, {"source": "wikihelploader_wikihelploader_trygethelp", "target": "wikihelploader_wikihelploader_tryloadlayer1", "relation": "calls", "confidence": "EXTRACTED", "source_file": "D:\\Excel Add-in V2\\sources\\OfficeCLI-main\\OfficeCLI-main\\src\\officecli\\WikiHelpLoader.cs", "source_location": "L62", "weight": 1.0}, {"source": "wikihelploader_wikihelploader_trygethelp", "target": "wikihelploader_wikihelploader_extractpropertysection", "relation": "calls", "confidence": "EXTRACTED", "source_file": "D:\\Excel Add-in V2\\sources\\OfficeCLI-main\\OfficeCLI-main\\src\\officecli\\WikiHelpLoader.cs", "source_location": "L74", "weight": 1.0}, {"source": "wikihelploader_wikihelploader_tryloadlayer1", "target": "wikihelploader_wikihelploader_tryloadandrender", "relation": "calls", "confidence": "EXTRACTED", "source_file": "D:\\Excel Add-in V2\\sources\\OfficeCLI-main\\OfficeCLI-main\\src\\officecli\\WikiHelpLoader.cs", "source_location": "L89", "weight": 1.0}, {"source": "wikihelploader_wikihelploader_tryloadlayer1", "target": "wikihelploader_wikihelploader_findwikifiles", "relation": "calls", "confidence": "EXTRACTED", "source_file": "D:\\Excel Add-in V2\\sources\\OfficeCLI-main\\OfficeCLI-main\\src\\officecli\\WikiHelpLoader.cs", "source_location": "L96", "weight": 1.0}, {"source": "wikihelploader_wikihelploader_tryloadandrender", "target": "wikihelploader_wikihelploader_tryloadfromlocalwiki", "relation": "calls", "confidence": "EXTRACTED", "source_file": "D:\\Excel Add-in V2\\sources\\OfficeCLI-main\\OfficeCLI-main\\src\\officecli\\WikiHelpLoader.cs", "source_location": "L206", "weight": 1.0}, {"source": "wikihelploader_wikihelploader_tryloadandrender", "target": "wikihelploader_wikihelploader_rendermarkdown", "relation": "calls", "confidence": "EXTRACTED", "source_file": "D:\\Excel Add-in V2\\sources\\OfficeCLI-main\\OfficeCLI-main\\src\\officecli\\WikiHelpLoader.cs", "source_location": "L207", "weight": 1.0}, {"source": "wikihelploader_wikihelploader_tryloadandrender", "target": "wikihelploader_wikihelploader_tryloadfromembeddedresource", "relation": "calls", "confidence": "EXTRACTED", "source_file": "D:\\Excel Add-in V2\\sources\\OfficeCLI-main\\OfficeCLI-main\\src\\officecli\\WikiHelpLoader.cs", "source_location": "L210", "weight": 1.0}, {"source": "wikihelploader_wikihelploader_tryloadfromlocalwiki", "target": "wikihelploader_wikihelploader_findlocalwikidir", "relation": "calls", "confidence": "EXTRACTED", "source_file": "D:\\Excel Add-in V2\\sources\\OfficeCLI-main\\OfficeCLI-main\\src\\officecli\\WikiHelpLoader.cs", "source_location": "L218", "weight": 1.0}, {"source": "wikihelploader_wikihelploader_findwikifiles", "target": "wikihelploader_wikihelploader_findlocalwikidir", "relation": "calls", "confidence": "EXTRACTED", "source_file": "D:\\Excel Add-in V2\\sources\\OfficeCLI-main\\OfficeCLI-main\\src\\officecli\\WikiHelpLoader.cs", "source_location": "L288", "weight": 1.0}], "raw_calls": [{"caller_nid": "wikihelploader_wikihelploader_trygethelp", "callee": "GetValueOrDefault", "source_file": "D:\\Excel Add-in V2\\sources\\OfficeCLI-main\\OfficeCLI-main\\src\\officecli\\WikiHelpLoader.cs", "source_location": "L56"}, {"caller_nid": "wikihelploader_wikihelploader_trygethelp", "callee": "TryGetValue", "source_file": "D:\\Excel Add-in V2\\sources\\OfficeCLI-main\\OfficeCLI-main\\src\\officecli\\WikiHelpLoader.cs", "source_location": "L66"}, {"caller_nid": "wikihelploader_wikihelploader_tryloadlayer1", "callee": "TryGetValue", "source_file": "D:\\Excel Add-in V2\\sources\\OfficeCLI-main\\OfficeCLI-main\\src\\officecli\\WikiHelpLoader.cs", "source_location": "L86"}, {"caller_nid": "wikihelploader_wikihelploader_tryloadlayer1", "callee": "TryGetValue", "source_file": "D:\\Excel Add-in V2\\sources\\OfficeCLI-main\\OfficeCLI-main\\src\\officecli\\WikiHelpLoader.cs", "source_location": "L93"}, {"caller_nid": "wikihelploader_wikihelploader_tryloadlayer1", "callee": "AppendLine", "source_file": "D:\\Excel Add-in V2\\sources\\OfficeCLI-main\\OfficeCLI-main\\src\\officecli\\WikiHelpLoader.cs", "source_location": "L102"}, {"caller_nid": "wikihelploader_wikihelploader_tryloadlayer1", "callee": "AppendLine", "source_file": "D:\\Excel Add-in V2\\sources\\OfficeCLI-main\\OfficeCLI-main\\src\\officecli\\WikiHelpLoader.cs", "source_location": "L103"}, {"caller_nid": "wikihelploader_wikihelploader_tryloadlayer1", "callee": "AppendLine", "source_file": "D:\\Excel Add-in V2\\sources\\OfficeCLI-main\\OfficeCLI-main\\src\\officecli\\WikiHelpLoader.cs", "source_location": "L112"}, {"caller_nid": "wikihelploader_wikihelploader_tryloadlayer1", "callee": "AppendLine", "source_file": "D:\\Excel Add-in V2\\sources\\OfficeCLI-main\\OfficeCLI-main\\src\\officecli\\WikiHelpLoader.cs", "source_location": "L113"}, {"caller_nid": "wikihelploader_wikihelploader_tryloadlayer1", "callee": "TrimEnd", "source_file": "D:\\Excel Add-in V2\\sources\\OfficeCLI-main\\OfficeCLI-main\\src\\officecli\\WikiHelpLoader.cs", "source_location": "L117"}, {"caller_nid": "wikihelploader_wikihelploader_tryloadlayer1", "callee": "ToString", "source_file": "D:\\Excel Add-in V2\\sources\\OfficeCLI-main\\OfficeCLI-main\\src\\officecli\\WikiHelpLoader.cs", "source_location": "L117"}, {"caller_nid": "wikihelploader_wikihelploader_extractpropertysection", "callee": "Split", "source_file": "D:\\Excel Add-in V2\\sources\\OfficeCLI-main\\OfficeCLI-main\\src\\officecli\\WikiHelpLoader.cs", "source_location": "L127"}, {"caller_nid": "wikihelploader_wikihelploader_extractpropertysection", "callee": "Contains", "source_file": "D:\\Excel Add-in V2\\sources\\OfficeCLI-main\\OfficeCLI-main\\src\\officecli\\WikiHelpLoader.cs", "source_location": "L135"}, {"caller_nid": "wikihelploader_wikihelploader_extractpropertysection", "callee": "Contains", "source_file": "D:\\Excel Add-in V2\\sources\\OfficeCLI-main\\OfficeCLI-main\\src\\officecli\\WikiHelpLoader.cs", "source_location": "L136"}, {"caller_nid": "wikihelploader_wikihelploader_extractpropertysection", "callee": "Contains", "source_file": "D:\\Excel Add-in V2\\sources\\OfficeCLI-main\\OfficeCLI-main\\src\\officecli\\WikiHelpLoader.cs", "source_location": "L137"}, {"caller_nid": "wikihelploader_wikihelploader_extractpropertysection", "callee": "Contains", "source_file": "D:\\Excel Add-in V2\\sources\\OfficeCLI-main\\OfficeCLI-main\\src\\officecli\\WikiHelpLoader.cs", "source_location": "L138"}, {"caller_nid": "wikihelploader_wikihelploader_extractpropertysection", "callee": "Contains", "source_file": "D:\\Excel Add-in V2\\sources\\OfficeCLI-main\\OfficeCLI-main\\src\\officecli\\WikiHelpLoader.cs", "source_location": "L139"}, {"caller_nid": "wikihelploader_wikihelploader_extractpropertysection", "callee": "StartsWith", "source_file": "D:\\Excel Add-in V2\\sources\\OfficeCLI-main\\OfficeCLI-main\\src\\officecli\\WikiHelpLoader.cs", "source_location": "L146"}, {"caller_nid": "wikihelploader_wikihelploader_extractpropertysection", "callee": "TrimStart", "source_file": "D:\\Excel Add-in V2\\sources\\OfficeCLI-main\\OfficeCLI-main\\src\\officecli\\WikiHelpLoader.cs", "source_location": "L146"}, {"caller_nid": "wikihelploader_wikihelploader_extractpropertysection", "callee": "Contains", "source_file": "D:\\Excel Add-in V2\\sources\\OfficeCLI-main\\OfficeCLI-main\\src\\officecli\\WikiHelpLoader.cs", "source_location": "L146"}, {"caller_nid": "wikihelploader_wikihelploader_extractpropertysection", "callee": "AppendLine", "source_file": "D:\\Excel Add-in V2\\sources\\OfficeCLI-main\\OfficeCLI-main\\src\\officecli\\WikiHelpLoader.cs", "source_location": "L148"}, {"caller_nid": "wikihelploader_wikihelploader_extractpropertysection", "callee": "AppendLine", "source_file": "D:\\Excel Add-in V2\\sources\\OfficeCLI-main\\OfficeCLI-main\\src\\officecli\\WikiHelpLoader.cs", "source_location": "L149"}, {"caller_nid": "wikihelploader_wikihelploader_extractpropertysection", "callee": "AppendLine", "source_file": "D:\\Excel Add-in V2\\sources\\OfficeCLI-main\\OfficeCLI-main\\src\\officecli\\WikiHelpLoader.cs", "source_location": "L155"}, {"caller_nid": "wikihelploader_wikihelploader_extractpropertysection", "callee": "Escape", "source_file": "D:\\Excel Add-in V2\\sources\\OfficeCLI-main\\OfficeCLI-main\\src\\officecli\\WikiHelpLoader.cs", "source_location": "L161"}, {"caller_nid": "wikihelploader_wikihelploader_extractpropertysection", "callee": "Match", "source_file": "D:\\Excel Add-in V2\\sources\\OfficeCLI-main\\OfficeCLI-main\\src\\officecli\\WikiHelpLoader.cs", "source_location": "L169"}, {"caller_nid": "wikihelploader_wikihelploader_extractpropertysection", "callee": "AppendLine", "source_file": "D:\\Excel Add-in V2\\sources\\OfficeCLI-main\\OfficeCLI-main\\src\\officecli\\WikiHelpLoader.cs", "source_location": "L174"}, {"caller_nid": "wikihelploader_wikihelploader_extractpropertysection", "callee": "AppendLine", "source_file": "D:\\Excel Add-in V2\\sources\\OfficeCLI-main\\OfficeCLI-main\\src\\officecli\\WikiHelpLoader.cs", "source_location": "L175"}, {"caller_nid": "wikihelploader_wikihelploader_extractpropertysection", "callee": "Match", "source_file": "D:\\Excel Add-in V2\\sources\\OfficeCLI-main\\OfficeCLI-main\\src\\officecli\\WikiHelpLoader.cs", "source_location": "L183"}, {"caller_nid": "wikihelploader_wikihelploader_extractpropertysection", "callee": "AppendLine", "source_file": "D:\\Excel Add-in V2\\sources\\OfficeCLI-main\\OfficeCLI-main\\src\\officecli\\WikiHelpLoader.cs", "source_location": "L190"}, {"caller_nid": "wikihelploader_wikihelploader_extractpropertysection", "callee": "TrimEnd", "source_file": "D:\\Excel Add-in V2\\sources\\OfficeCLI-main\\OfficeCLI-main\\src\\officecli\\WikiHelpLoader.cs", "source_location": "L194"}, {"caller_nid": "wikihelploader_wikihelploader_extractpropertysection", "callee": "ToString", "source_file": "D:\\Excel Add-in V2\\sources\\OfficeCLI-main\\OfficeCLI-main\\src\\officecli\\WikiHelpLoader.cs", "source_location": "L194"}, {"caller_nid": "wikihelploader_wikihelploader_tryloadfromlocalwiki", "callee": "Combine", "source_file": "D:\\Excel Add-in V2\\sources\\OfficeCLI-main\\OfficeCLI-main\\src\\officecli\\WikiHelpLoader.cs", "source_location": "L220"}, {"caller_nid": "wikihelploader_wikihelploader_tryloadfromlocalwiki", "callee": "Exists", "source_file": "D:\\Excel Add-in V2\\sources\\OfficeCLI-main\\OfficeCLI-main\\src\\officecli\\WikiHelpLoader.cs", "source_location": "L221"}, {"caller_nid": "wikihelploader_wikihelploader_tryloadfromlocalwiki", "callee": "ReadAllText", "source_file": "D:\\Excel Add-in V2\\sources\\OfficeCLI-main\\OfficeCLI-main\\src\\officecli\\WikiHelpLoader.cs", "source_location": "L221"}, {"caller_nid": "wikihelploader_wikihelploader_tryloadfromembeddedresource", "callee": "GetExecutingAssembly", "source_file": "D:\\Excel Add-in V2\\sources\\OfficeCLI-main\\OfficeCLI-main\\src\\officecli\\WikiHelpLoader.cs", "source_location": "L226"}, {"caller_nid": "wikihelploader_wikihelploader_tryloadfromembeddedresource", "callee": "FirstOrDefault", "source_file": "D:\\Excel Add-in V2\\sources\\OfficeCLI-main\\OfficeCLI-main\\src\\officecli\\WikiHelpLoader.cs", "source_location": "L227"}, {"caller_nid": "wikihelploader_wikihelploader_tryloadfromembeddedresource", "callee": "GetManifestResourceNames", "source_file": "D:\\Excel Add-in V2\\sources\\OfficeCLI-main\\OfficeCLI-main\\src\\officecli\\WikiHelpLoader.cs", "source_location": "L227"}, {"caller_nid": "wikihelploader_wikihelploader_tryloadfromembeddedresource", "callee": "EndsWith", "source_file": "D:\\Excel Add-in V2\\sources\\OfficeCLI-main\\OfficeCLI-main\\src\\officecli\\WikiHelpLoader.cs", "source_location": "L228"}, {"caller_nid": "wikihelploader_wikihelploader_tryloadfromembeddedresource", "callee": "Replace", "source_file": "D:\\Excel Add-in V2\\sources\\OfficeCLI-main\\OfficeCLI-main\\src\\officecli\\WikiHelpLoader.cs", "source_location": "L228"}, {"caller_nid": "wikihelploader_wikihelploader_tryloadfromembeddedresource", "callee": "Replace", "source_file": "D:\\Excel Add-in V2\\sources\\OfficeCLI-main\\OfficeCLI-main\\src\\officecli\\WikiHelpLoader.cs", "source_location": "L228"}, {"caller_nid": "wikihelploader_wikihelploader_tryloadfromembeddedresource", "callee": "FirstOrDefault", "source_file": "D:\\Excel Add-in V2\\sources\\OfficeCLI-main\\OfficeCLI-main\\src\\officecli\\WikiHelpLoader.cs", "source_location": "L232"}, {"caller_nid": "wikihelploader_wikihelploader_tryloadfromembeddedresource", "callee": "GetManifestResourceNames", "source_file": "D:\\Excel Add-in V2\\sources\\OfficeCLI-main\\OfficeCLI-main\\src\\officecli\\WikiHelpLoader.cs", "source_location": "L232"}, {"caller_nid": "wikihelploader_wikihelploader_tryloadfromembeddedresource", "callee": "EndsWith", "source_file": "D:\\Excel Add-in V2\\sources\\OfficeCLI-main\\OfficeCLI-main\\src\\officecli\\WikiHelpLoader.cs", "source_location": "L233"}, {"caller_nid": "wikihelploader_wikihelploader_tryloadfromembeddedresource", "callee": "GetManifestResourceStream", "source_file": "D:\\Excel Add-in V2\\sources\\OfficeCLI-main\\OfficeCLI-main\\src\\officecli\\WikiHelpLoader.cs", "source_location": "L237"}, {"caller_nid": "wikihelploader_wikihelploader_tryloadfromembeddedresource", "callee": "ReadToEnd", "source_file": "D:\\Excel Add-in V2\\sources\\OfficeCLI-main\\OfficeCLI-main\\src\\officecli\\WikiHelpLoader.cs", "source_location": "L240"}, {"caller_nid": "wikihelploader_wikihelploader_findlocalwikidir", "callee": "GetCurrentDirectory", "source_file": "D:\\Excel Add-in V2\\sources\\OfficeCLI-main\\OfficeCLI-main\\src\\officecli\\WikiHelpLoader.cs", "source_location": "L254"}, {"caller_nid": "wikihelploader_wikihelploader_findlocalwikidir", "callee": "Exists", "source_file": "D:\\Excel Add-in V2\\sources\\OfficeCLI-main\\OfficeCLI-main\\src\\officecli\\WikiHelpLoader.cs", "source_location": "L257"}, {"caller_nid": "wikihelploader_wikihelploader_findlocalwikidir", "callee": "Combine", "source_file": "D:\\Excel Add-in V2\\sources\\OfficeCLI-main\\OfficeCLI-main\\src\\officecli\\WikiHelpLoader.cs", "source_location": "L257"}, {"caller_nid": "wikihelploader_wikihelploader_findlocalwikidir", "callee": "Combine", "source_file": "D:\\Excel Add-in V2\\sources\\OfficeCLI-main\\OfficeCLI-main\\src\\officecli\\WikiHelpLoader.cs", "source_location": "L260"}, {"caller_nid": "wikihelploader_wikihelploader_findlocalwikidir", "callee": "Exists", "source_file": "D:\\Excel Add-in V2\\sources\\OfficeCLI-main\\OfficeCLI-main\\src\\officecli\\WikiHelpLoader.cs", "source_location": "L261"}, {"caller_nid": "wikihelploader_wikihelploader_findwikifiles", "callee": "GetFiles", "source_file": "D:\\Excel Add-in V2\\sources\\OfficeCLI-main\\OfficeCLI-main\\src\\officecli\\WikiHelpLoader.cs", "source_location": "L293"}, {"caller_nid": "wikihelploader_wikihelploader_findwikifiles", "callee": "Add", "source_file": "D:\\Excel Add-in V2\\sources\\OfficeCLI-main\\OfficeCLI-main\\src\\officecli\\WikiHelpLoader.cs", "source_location": "L294"}, {"caller_nid": "wikihelploader_wikihelploader_findwikifiles", "callee": "GetFileName", "source_file": "D:\\Excel Add-in V2\\sources\\OfficeCLI-main\\OfficeCLI-main\\src\\officecli\\WikiHelpLoader.cs", "source_location": "L294"}, {"caller_nid": "wikihelploader_wikihelploader_findwikifiles", "callee": "GetExecutingAssembly", "source_file": "D:\\Excel Add-in V2\\sources\\OfficeCLI-main\\OfficeCLI-main\\src\\officecli\\WikiHelpLoader.cs", "source_location": "L302"}, {"caller_nid": "wikihelploader_wikihelploader_findwikifiles", "callee": "Replace", "source_file": "D:\\Excel Add-in V2\\sources\\OfficeCLI-main\\OfficeCLI-main\\src\\officecli\\WikiHelpLoader.cs", "source_location": "L304"}, {"caller_nid": "wikihelploader_wikihelploader_findwikifiles", "callee": "Replace", "source_file": "D:\\Excel Add-in V2\\sources\\OfficeCLI-main\\OfficeCLI-main\\src\\officecli\\WikiHelpLoader.cs", "source_location": "L304"}, {"caller_nid": "wikihelploader_wikihelploader_findwikifiles", "callee": "Escape", "source_file": "D:\\Excel Add-in V2\\sources\\OfficeCLI-main\\OfficeCLI-main\\src\\officecli\\WikiHelpLoader.cs", "source_location": "L304"}, {"caller_nid": "wikihelploader_wikihelploader_findwikifiles", "callee": "GetManifestResourceNames", "source_file": "D:\\Excel Add-in V2\\sources\\OfficeCLI-main\\OfficeCLI-main\\src\\officecli\\WikiHelpLoader.cs", "source_location": "L307"}, {"caller_nid": "wikihelploader_wikihelploader_findwikifiles", "callee": "IsMatch", "source_file": "D:\\Excel Add-in V2\\sources\\OfficeCLI-main\\OfficeCLI-main\\src\\officecli\\WikiHelpLoader.cs", "source_location": "L309"}, {"caller_nid": "wikihelploader_wikihelploader_findwikifiles", "callee": "Split", "source_file": "D:\\Excel Add-in V2\\sources\\OfficeCLI-main\\OfficeCLI-main\\src\\officecli\\WikiHelpLoader.cs", "source_location": "L312"}, {"caller_nid": "wikihelploader_wikihelploader_findwikifiles", "callee": "Join", "source_file": "D:\\Excel Add-in V2\\sources\\OfficeCLI-main\\OfficeCLI-main\\src\\officecli\\WikiHelpLoader.cs", "source_location": "L316"}, {"caller_nid": "wikihelploader_wikihelploader_findwikifiles", "callee": "Skip", "source_file": "D:\\Excel Add-in V2\\sources\\OfficeCLI-main\\OfficeCLI-main\\src\\officecli\\WikiHelpLoader.cs", "source_location": "L316"}, {"caller_nid": "wikihelploader_wikihelploader_findwikifiles", "callee": "Add", "source_file": "D:\\Excel Add-in V2\\sources\\OfficeCLI-main\\OfficeCLI-main\\src\\officecli\\WikiHelpLoader.cs", "source_location": "L317"}, {"caller_nid": "wikihelploader_wikihelploader_findwikifiles", "callee": "Sort", "source_file": "D:\\Excel Add-in V2\\sources\\OfficeCLI-main\\OfficeCLI-main\\src\\officecli\\WikiHelpLoader.cs", "source_location": "L323"}, {"caller_nid": "wikihelploader_wikihelploader_rendermarkdown", "callee": "Split", "source_file": "D:\\Excel Add-in V2\\sources\\OfficeCLI-main\\OfficeCLI-main\\src\\officecli\\WikiHelpLoader.cs", "source_location": "L333"}, {"caller_nid": "wikihelploader_wikihelploader_rendermarkdown", "callee": "TrimStart", "source_file": "D:\\Excel Add-in V2\\sources\\OfficeCLI-main\\OfficeCLI-main\\src\\officecli\\WikiHelpLoader.cs", "source_location": "L341"}, {"caller_nid": "wikihelploader_wikihelploader_rendermarkdown", "callee": "StartsWith", "source_file": "D:\\Excel Add-in V2\\sources\\OfficeCLI-main\\OfficeCLI-main\\src\\officecli\\WikiHelpLoader.cs", "source_location": "L341"}, {"caller_nid": "wikihelploader_wikihelploader_rendermarkdown", "callee": "TrimStart", "source_file": "D:\\Excel Add-in V2\\sources\\OfficeCLI-main\\OfficeCLI-main\\src\\officecli\\WikiHelpLoader.cs", "source_location": "L341"}, {"caller_nid": "wikihelploader_wikihelploader_rendermarkdown", "callee": "Replace", "source_file": "D:\\Excel Add-in V2\\sources\\OfficeCLI-main\\OfficeCLI-main\\src\\officecli\\WikiHelpLoader.cs", "source_location": "L345"}, {"caller_nid": "wikihelploader_wikihelploader_rendermarkdown", "callee": "StartsWith", "source_file": "D:\\Excel Add-in V2\\sources\\OfficeCLI-main\\OfficeCLI-main\\src\\officecli\\WikiHelpLoader.cs", "source_location": "L349"}, {"caller_nid": "wikihelploader_wikihelploader_rendermarkdown", "callee": "TrimStart", "source_file": "D:\\Excel Add-in V2\\sources\\OfficeCLI-main\\OfficeCLI-main\\src\\officecli\\WikiHelpLoader.cs", "source_location": "L349"}, {"caller_nid": "wikihelploader_wikihelploader_rendermarkdown", "callee": "Replace", "source_file": "D:\\Excel Add-in V2\\sources\\OfficeCLI-main\\OfficeCLI-main\\src\\officecli\\WikiHelpLoader.cs", "source_location": "L350"}, {"caller_nid": "wikihelploader_wikihelploader_rendermarkdown", "callee": "AppendLine", "source_file": "D:\\Excel Add-in V2\\sources\\OfficeCLI-main\\OfficeCLI-main\\src\\officecli\\WikiHelpLoader.cs", "source_location": "L352"}, {"caller_nid": "wikihelploader_wikihelploader_rendermarkdown", "callee": "TrimEnd", "source_file": "D:\\Excel Add-in V2\\sources\\OfficeCLI-main\\OfficeCLI-main\\src\\officecli\\WikiHelpLoader.cs", "source_location": "L355"}, {"caller_nid": "wikihelploader_wikihelploader_rendermarkdown", "callee": "ToString", "source_file": "D:\\Excel Add-in V2\\sources\\OfficeCLI-main\\OfficeCLI-main\\src\\officecli\\WikiHelpLoader.cs", "source_location": "L355"}]}