{"nodes": [{"id": "d_excel_add_in_v2_sources_mcp_server_excel_main_mcp_server_excel_main_src_excelmcp_core_models_resulttypes_cs", "label": "ResultTypes.cs", "file_type": "code", "source_file": "D:\\Excel Add-in V2\\sources\\mcp-server-excel-main\\mcp-server-excel-main\\src\\ExcelMcp.Core\\Models\\ResultTypes.cs", "source_location": "L1"}, {"id": "resulttypes_resultbase", "label": "ResultBase", "file_type": "code", "source_file": "D:\\Excel Add-in V2\\sources\\mcp-server-excel-main\\mcp-server-excel-main\\src\\ExcelMcp.Core\\Models\\ResultTypes.cs", "source_location": "L11"}, {"id": "resulttypes_operationresult", "label": "OperationResult", "file_type": "code", "source_file": "D:\\Excel Add-in V2\\sources\\mcp-server-excel-main\\mcp-server-excel-main\\src\\ExcelMcp.Core\\Models\\ResultTypes.cs", "source_location": "L34"}, {"id": "resulttypes_renameresult", "label": "RenameResult", "file_type": "code", "source_file": "D:\\Excel Add-in V2\\sources\\mcp-server-excel-main\\mcp-server-excel-main\\src\\ExcelMcp.Core\\Models\\ResultTypes.cs", "source_location": "L52"}, {"id": "resulttypes_worksheetlistresult", "label": "WorksheetListResult", "file_type": "code", "source_file": "D:\\Excel Add-in V2\\sources\\mcp-server-excel-main\\mcp-server-excel-main\\src\\ExcelMcp.Core\\Models\\ResultTypes.cs", "source_location": "L85"}, {"id": "resulttypes_worksheetinfo", "label": "WorksheetInfo", "file_type": "code", "source_file": "D:\\Excel Add-in V2\\sources\\mcp-server-excel-main\\mcp-server-excel-main\\src\\ExcelMcp.Core\\Models\\ResultTypes.cs", "source_location": "L96"}, {"id": "resulttypes_tabcolorresult", "label": "TabColorResult", "file_type": "code", "source_file": "D:\\Excel Add-in V2\\sources\\mcp-server-excel-main\\mcp-server-excel-main\\src\\ExcelMcp.Core\\Models\\ResultTypes.cs", "source_location": "L138"}, {"id": "resulttypes_sheetvisibilityresult", "label": "SheetVisibilityResult", "file_type": "code", "source_file": "D:\\Excel Add-in V2\\sources\\mcp-server-excel-main\\mcp-server-excel-main\\src\\ExcelMcp.Core\\Models\\ResultTypes.cs", "source_location": "L173"}, {"id": "resulttypes_worksheetdataresult", "label": "WorksheetDataResult", "file_type": "code", "source_file": "D:\\Excel Add-in V2\\sources\\mcp-server-excel-main\\mcp-server-excel-main\\src\\ExcelMcp.Core\\Models\\ResultTypes.cs", "source_location": "L189"}, {"id": "resulttypes_powerquerylistresult", "label": "PowerQueryListResult", "file_type": "code", "source_file": "D:\\Excel Add-in V2\\sources\\mcp-server-excel-main\\mcp-server-excel-main\\src\\ExcelMcp.Core\\Models\\ResultTypes.cs", "source_location": "L225"}, {"id": "resulttypes_powerqueryinfo", "label": "PowerQueryInfo", "file_type": "code", "source_file": "D:\\Excel Add-in V2\\sources\\mcp-server-excel-main\\mcp-server-excel-main\\src\\ExcelMcp.Core\\Models\\ResultTypes.cs", "source_location": "L236"}, {"id": "resulttypes_powerqueryviewresult", "label": "PowerQueryViewResult", "file_type": "code", "source_file": "D:\\Excel Add-in V2\\sources\\mcp-server-excel-main\\mcp-server-excel-main\\src\\ExcelMcp.Core\\Models\\ResultTypes.cs", "source_location": "L262"}, {"id": "resulttypes_powerqueryloadconfigresult", "label": "PowerQueryLoadConfigResult", "file_type": "code", "source_file": "D:\\Excel Add-in V2\\sources\\mcp-server-excel-main\\mcp-server-excel-main\\src\\ExcelMcp.Core\\Models\\ResultTypes.cs", "source_location": "L319"}, {"id": "resulttypes_powerqueryloadtodatamodelresult", "label": "PowerQueryLoadToDataModelResult", "file_type": "code", "source_file": "D:\\Excel Add-in V2\\sources\\mcp-server-excel-main\\mcp-server-excel-main\\src\\ExcelMcp.Core\\Models\\ResultTypes.cs", "source_location": "L352"}, {"id": "resulttypes_powerqueryloadtotableresult", "label": "PowerQueryLoadToTableResult", "file_type": "code", "source_file": "D:\\Excel Add-in V2\\sources\\mcp-server-excel-main\\mcp-server-excel-main\\src\\ExcelMcp.Core\\Models\\ResultTypes.cs", "source_location": "L389"}, {"id": "resulttypes_powerqueryloadtobothresult", "label": "PowerQueryLoadToBothResult", "file_type": "code", "source_file": "D:\\Excel Add-in V2\\sources\\mcp-server-excel-main\\mcp-server-excel-main\\src\\ExcelMcp.Core\\Models\\ResultTypes.cs", "source_location": "L426"}, {"id": "resulttypes_powerquerycreateresult", "label": "PowerQueryCreateResult", "file_type": "code", "source_file": "D:\\Excel Add-in V2\\sources\\mcp-server-excel-main\\mcp-server-excel-main\\src\\ExcelMcp.Core\\Models\\ResultTypes.cs", "source_location": "L478"}, {"id": "resulttypes_powerqueryloadresult", "label": "PowerQueryLoadResult", "file_type": "code", "source_file": "D:\\Excel Add-in V2\\sources\\mcp-server-excel-main\\mcp-server-excel-main\\src\\ExcelMcp.Core\\Models\\ResultTypes.cs", "source_location": "L522"}, {"id": "resulttypes_powerqueryvalidationresult", "label": "PowerQueryValidationResult", "file_type": "code", "source_file": "D:\\Excel Add-in V2\\sources\\mcp-server-excel-main\\mcp-server-excel-main\\src\\ExcelMcp.Core\\Models\\ResultTypes.cs", "source_location": "L566"}, {"id": "resulttypes_namedrangelistresult", "label": "NamedRangeListResult", "file_type": "code", "source_file": "D:\\Excel Add-in V2\\sources\\mcp-server-excel-main\\mcp-server-excel-main\\src\\ExcelMcp.Core\\Models\\ResultTypes.cs", "source_location": "L588"}, {"id": "resulttypes_namedrangeinfo", "label": "NamedRangeInfo", "file_type": "code", "source_file": "D:\\Excel Add-in V2\\sources\\mcp-server-excel-main\\mcp-server-excel-main\\src\\ExcelMcp.Core\\Models\\ResultTypes.cs", "source_location": "L599"}, {"id": "resulttypes_namedrangevalue", "label": "NamedRangeValue", "file_type": "code", "source_file": "D:\\Excel Add-in V2\\sources\\mcp-server-excel-main\\mcp-server-excel-main\\src\\ExcelMcp.Core\\Models\\ResultTypes.cs", "source_location": "L626"}, {"id": "resulttypes_namedrangevalueresult", "label": "NamedRangeValueResult", "file_type": "code", "source_file": "D:\\Excel Add-in V2\\sources\\mcp-server-excel-main\\mcp-server-excel-main\\src\\ExcelMcp.Core\\Models\\ResultTypes.cs", "source_location": "L653"}, {"id": "resulttypes_vbalistresult", "label": "VbaListResult", "file_type": "code", "source_file": "D:\\Excel Add-in V2\\sources\\mcp-server-excel-main\\mcp-server-excel-main\\src\\ExcelMcp.Core\\Models\\ResultTypes.cs", "source_location": "L680"}, {"id": "resulttypes_vbaviewresult", "label": "VbaViewResult", "file_type": "code", "source_file": "D:\\Excel Add-in V2\\sources\\mcp-server-excel-main\\mcp-server-excel-main\\src\\ExcelMcp.Core\\Models\\ResultTypes.cs", "source_location": "L691"}, {"id": "resulttypes_scriptinfo", "label": "ScriptInfo", "file_type": "code", "source_file": "D:\\Excel Add-in V2\\sources\\mcp-server-excel-main\\mcp-server-excel-main\\src\\ExcelMcp.Core\\Models\\ResultTypes.cs", "source_location": "L722"}, {"id": "resulttypes_filevalidationinfo", "label": "FileValidationInfo", "file_type": "code", "source_file": "D:\\Excel Add-in V2\\sources\\mcp-server-excel-main\\mcp-server-excel-main\\src\\ExcelMcp.Core\\Models\\ResultTypes.cs", "source_location": "L748"}, {"id": "resulttypes_cellvalueresult", "label": "CellValueResult", "file_type": "code", "source_file": "D:\\Excel Add-in V2\\sources\\mcp-server-excel-main\\mcp-server-excel-main\\src\\ExcelMcp.Core\\Models\\ResultTypes.cs", "source_location": "L798"}, {"id": "resulttypes_rangevalueresult", "label": "RangeValueResult", "file_type": "code", "source_file": "D:\\Excel Add-in V2\\sources\\mcp-server-excel-main\\mcp-server-excel-main\\src\\ExcelMcp.Core\\Models\\ResultTypes.cs", "source_location": "L826"}, {"id": "resulttypes_rangeformularesult", "label": "RangeFormulaResult", "file_type": "code", "source_file": "D:\\Excel Add-in V2\\sources\\mcp-server-excel-main\\mcp-server-excel-main\\src\\ExcelMcp.Core\\Models\\ResultTypes.cs", "source_location": "L857"}, {"id": "resulttypes_rangecellerror", "label": "RangeCellError", "file_type": "code", "source_file": "D:\\Excel Add-in V2\\sources\\mcp-server-excel-main\\mcp-server-excel-main\\src\\ExcelMcp.Core\\Models\\ResultTypes.cs", "source_location": "L900"}, {"id": "resulttypes_rangeformulavalidationresult", "label": "RangeFormulaValidationResult", "file_type": "code", "source_file": "D:\\Excel Add-in V2\\sources\\mcp-server-excel-main\\mcp-server-excel-main\\src\\ExcelMcp.Core\\Models\\ResultTypes.cs", "source_location": "L944"}, {"id": "resulttypes_formulavalidationerror", "label": "FormulaValidationError", "file_type": "code", "source_file": "D:\\Excel Add-in V2\\sources\\mcp-server-excel-main\\mcp-server-excel-main\\src\\ExcelMcp.Core\\Models\\ResultTypes.cs", "source_location": "L997"}, {"id": "resulttypes_formulavalidationwarning", "label": "FormulaValidationWarning", "file_type": "code", "source_file": "D:\\Excel Add-in V2\\sources\\mcp-server-excel-main\\mcp-server-excel-main\\src\\ExcelMcp.Core\\Models\\ResultTypes.cs", "source_location": "L1039"}, {"id": "resulttypes_rangefindresult", "label": "RangeFindResult", "file_type": "code", "source_file": "D:\\Excel Add-in V2\\sources\\mcp-server-excel-main\\mcp-server-excel-main\\src\\ExcelMcp.Core\\Models\\ResultTypes.cs", "source_location": "L1065"}, {"id": "resulttypes_rangecell", "label": "RangeCell", "file_type": "code", "source_file": "D:\\Excel Add-in V2\\sources\\mcp-server-excel-main\\mcp-server-excel-main\\src\\ExcelMcp.Core\\Models\\ResultTypes.cs", "source_location": "L1091"}, {"id": "resulttypes_rangeinforesult", "label": "RangeInfoResult", "file_type": "code", "source_file": "D:\\Excel Add-in V2\\sources\\mcp-server-excel-main\\mcp-server-excel-main\\src\\ExcelMcp.Core\\Models\\ResultTypes.cs", "source_location": "L1118"}, {"id": "resulttypes_rangehyperlinkresult", "label": "RangeHyperlinkResult", "file_type": "code", "source_file": "D:\\Excel Add-in V2\\sources\\mcp-server-excel-main\\mcp-server-excel-main\\src\\ExcelMcp.Core\\Models\\ResultTypes.cs", "source_location": "L1174"}, {"id": "resulttypes_rangestyleresult", "label": "RangeStyleResult", "file_type": "code", "source_file": "D:\\Excel Add-in V2\\sources\\mcp-server-excel-main\\mcp-server-excel-main\\src\\ExcelMcp.Core\\Models\\ResultTypes.cs", "source_location": "L1195"}, {"id": "resulttypes_vbatrustresult", "label": "VbaTrustResult", "file_type": "code", "source_file": "D:\\Excel Add-in V2\\sources\\mcp-server-excel-main\\mcp-server-excel-main\\src\\ExcelMcp.Core\\Models\\ResultTypes.cs", "source_location": "L1227"}, {"id": "resulttypes_powerqueryrefreshresult", "label": "PowerQueryRefreshResult", "file_type": "code", "source_file": "D:\\Excel Add-in V2\\sources\\mcp-server-excel-main\\mcp-server-excel-main\\src\\ExcelMcp.Core\\Models\\ResultTypes.cs", "source_location": "L1283"}, {"id": "resulttypes_powerqueryerrorcheckresult", "label": "PowerQueryErrorCheckResult", "file_type": "code", "source_file": "D:\\Excel Add-in V2\\sources\\mcp-server-excel-main\\mcp-server-excel-main\\src\\ExcelMcp.Core\\Models\\ResultTypes.cs", "source_location": "L1320"}, {"id": "resulttypes_powerqueryevaluateresult", "label": "PowerQueryEvaluateResult", "file_type": "code", "source_file": "D:\\Excel Add-in V2\\sources\\mcp-server-excel-main\\mcp-server-excel-main\\src\\ExcelMcp.Core\\Models\\ResultTypes.cs", "source_location": "L1358"}, {"id": "resulttypes_connectionlistresult", "label": "ConnectionListResult", "file_type": "code", "source_file": "D:\\Excel Add-in V2\\sources\\mcp-server-excel-main\\mcp-server-excel-main\\src\\ExcelMcp.Core\\Models\\ResultTypes.cs", "source_location": "L1391"}, {"id": "resulttypes_connectioninfo", "label": "ConnectionInfo", "file_type": "code", "source_file": "D:\\Excel Add-in V2\\sources\\mcp-server-excel-main\\mcp-server-excel-main\\src\\ExcelMcp.Core\\Models\\ResultTypes.cs", "source_location": "L1402"}, {"id": "resulttypes_connectionviewresult", "label": "ConnectionViewResult", "file_type": "code", "source_file": "D:\\Excel Add-in V2\\sources\\mcp-server-excel-main\\mcp-server-excel-main\\src\\ExcelMcp.Core\\Models\\ResultTypes.cs", "source_location": "L1445"}, {"id": "resulttypes_connectionpropertiesresult", "label": "ConnectionPropertiesResult", "file_type": "code", "source_file": "D:\\Excel Add-in V2\\sources\\mcp-server-excel-main\\mcp-server-excel-main\\src\\ExcelMcp.Core\\Models\\ResultTypes.cs", "source_location": "L1488"}, {"id": "resulttypes_datamodeltablelistresult", "label": "DataModelTableListResult", "file_type": "code", "source_file": "D:\\Excel Add-in V2\\sources\\mcp-server-excel-main\\mcp-server-excel-main\\src\\ExcelMcp.Core\\Models\\ResultTypes.cs", "source_location": "L1523"}, {"id": "resulttypes_datamodeltableinfo", "label": "DataModelTableInfo", "file_type": "code", "source_file": "D:\\Excel Add-in V2\\sources\\mcp-server-excel-main\\mcp-server-excel-main\\src\\ExcelMcp.Core\\Models\\ResultTypes.cs", "source_location": "L1534"}, {"id": "resulttypes_datamodelmeasurelistresult", "label": "DataModelMeasureListResult", "file_type": "code", "source_file": "D:\\Excel Add-in V2\\sources\\mcp-server-excel-main\\mcp-server-excel-main\\src\\ExcelMcp.Core\\Models\\ResultTypes.cs", "source_location": "L1555"}, {"id": "resulttypes_datamodelmeasureinfo", "label": "DataModelMeasureInfo", "file_type": "code", "source_file": "D:\\Excel Add-in V2\\sources\\mcp-server-excel-main\\mcp-server-excel-main\\src\\ExcelMcp.Core\\Models\\ResultTypes.cs", "source_location": "L1566"}, {"id": "resulttypes_measureformatinfo", "label": "MeasureFormatInfo", "file_type": "code", "source_file": "D:\\Excel Add-in V2\\sources\\mcp-server-excel-main\\mcp-server-excel-main\\src\\ExcelMcp.Core\\Models\\ResultTypes.cs", "source_location": "L1594"}, {"id": "resulttypes_datamodelmeasureviewresult", "label": "DataModelMeasureViewResult", "file_type": "code", "source_file": "D:\\Excel Add-in V2\\sources\\mcp-server-excel-main\\mcp-server-excel-main\\src\\ExcelMcp.Core\\Models\\ResultTypes.cs", "source_location": "L1623"}, {"id": "resulttypes_datamodelrelationshiplistresult", "label": "DataModelRelationshipListResult", "file_type": "code", "source_file": "D:\\Excel Add-in V2\\sources\\mcp-server-excel-main\\mcp-server-excel-main\\src\\ExcelMcp.Core\\Models\\ResultTypes.cs", "source_location": "L1662"}, {"id": "resulttypes_datamodelrelationshipviewresult", "label": "DataModelRelationshipViewResult", "file_type": "code", "source_file": "D:\\Excel Add-in V2\\sources\\mcp-server-excel-main\\mcp-server-excel-main\\src\\ExcelMcp.Core\\Models\\ResultTypes.cs", "source_location": "L1673"}, {"id": "resulttypes_datamodelrelationshipinfo", "label": "DataModelRelationshipInfo", "file_type": "code", "source_file": "D:\\Excel Add-in V2\\sources\\mcp-server-excel-main\\mcp-server-excel-main\\src\\ExcelMcp.Core\\Models\\ResultTypes.cs", "source_location": "L1685"}, {"id": "resulttypes_datamodelvalidationresult", "label": "DataModelValidationResult", "file_type": "code", "source_file": "D:\\Excel Add-in V2\\sources\\mcp-server-excel-main\\mcp-server-excel-main\\src\\ExcelMcp.Core\\Models\\ResultTypes.cs", "source_location": "L1716"}, {"id": "resulttypes_datamodelcalculatedcolumnlistresult", "label": "DataModelCalculatedColumnListResult", "file_type": "code", "source_file": "D:\\Excel Add-in V2\\sources\\mcp-server-excel-main\\mcp-server-excel-main\\src\\ExcelMcp.Core\\Models\\ResultTypes.cs", "source_location": "L1738"}, {"id": "resulttypes_datamodelcalculatedcolumninfo", "label": "DataModelCalculatedColumnInfo", "file_type": "code", "source_file": "D:\\Excel Add-in V2\\sources\\mcp-server-excel-main\\mcp-server-excel-main\\src\\ExcelMcp.Core\\Models\\ResultTypes.cs", "source_location": "L1749"}, {"id": "resulttypes_datamodelcalculatedcolumnviewresult", "label": "DataModelCalculatedColumnViewResult", "file_type": "code", "source_file": "D:\\Excel Add-in V2\\sources\\mcp-server-excel-main\\mcp-server-excel-main\\src\\ExcelMcp.Core\\Models\\ResultTypes.cs", "source_location": "L1781"}, {"id": "resulttypes_daxevaluateresult", "label": "DaxEvaluateResult", "file_type": "code", "source_file": "D:\\Excel Add-in V2\\sources\\mcp-server-excel-main\\mcp-server-excel-main\\src\\ExcelMcp.Core\\Models\\ResultTypes.cs", "source_location": "L1818"}, {"id": "resulttypes_dmvqueryresult", "label": "DmvQueryResult", "file_type": "code", "source_file": "D:\\Excel Add-in V2\\sources\\mcp-server-excel-main\\mcp-server-excel-main\\src\\ExcelMcp.Core\\Models\\ResultTypes.cs", "source_location": "L1849"}, {"id": "resulttypes_tabledaxinforesult", "label": "TableDaxInfoResult", "file_type": "code", "source_file": "D:\\Excel Add-in V2\\sources\\mcp-server-excel-main\\mcp-server-excel-main\\src\\ExcelMcp.Core\\Models\\ResultTypes.cs", "source_location": "L1880"}, {"id": "resulttypes_tablelistresult", "label": "TableListResult", "file_type": "code", "source_file": "D:\\Excel Add-in V2\\sources\\mcp-server-excel-main\\mcp-server-excel-main\\src\\ExcelMcp.Core\\Models\\ResultTypes.cs", "source_location": "L1912"}, {"id": "resulttypes_tableinforesult", "label": "TableInfoResult", "file_type": "code", "source_file": "D:\\Excel Add-in V2\\sources\\mcp-server-excel-main\\mcp-server-excel-main\\src\\ExcelMcp.Core\\Models\\ResultTypes.cs", "source_location": "L1923"}, {"id": "resulttypes_tableinfo", "label": "TableInfo", "file_type": "code", "source_file": "D:\\Excel Add-in V2\\sources\\mcp-server-excel-main\\mcp-server-excel-main\\src\\ExcelMcp.Core\\Models\\ResultTypes.cs", "source_location": "L1935"}, {"id": "resulttypes_tabledataresult", "label": "TableDataResult", "file_type": "code", "source_file": "D:\\Excel Add-in V2\\sources\\mcp-server-excel-main\\mcp-server-excel-main\\src\\ExcelMcp.Core\\Models\\ResultTypes.cs", "source_location": "L1987"}, {"id": "resulttypes_tablefilterresult", "label": "TableFilterResult", "file_type": "code", "source_file": "D:\\Excel Add-in V2\\sources\\mcp-server-excel-main\\mcp-server-excel-main\\src\\ExcelMcp.Core\\Models\\ResultTypes.cs", "source_location": "L2018"}, {"id": "resulttypes_columnfilter", "label": "ColumnFilter", "file_type": "code", "source_file": "D:\\Excel Add-in V2\\sources\\mcp-server-excel-main\\mcp-server-excel-main\\src\\ExcelMcp.Core\\Models\\ResultTypes.cs", "source_location": "L2039"}, {"id": "resulttypes_tablestructuredreferenceresult", "label": "TableStructuredReferenceResult", "file_type": "code", "source_file": "D:\\Excel Add-in V2\\sources\\mcp-server-excel-main\\mcp-server-excel-main\\src\\ExcelMcp.Core\\Models\\ResultTypes.cs", "source_location": "L2103"}, {"id": "resulttypes_tablesortcolumn", "label": "TableSortColumn", "file_type": "code", "source_file": "D:\\Excel Add-in V2\\sources\\mcp-server-excel-main\\mcp-server-excel-main\\src\\ExcelMcp.Core\\Models\\ResultTypes.cs", "source_location": "L2150"}, {"id": "resulttypes_hyperlinkinfo", "label": "HyperlinkInfo", "file_type": "code", "source_file": "D:\\Excel Add-in V2\\sources\\mcp-server-excel-main\\mcp-server-excel-main\\src\\ExcelMcp.Core\\Models\\ResultTypes.cs", "source_location": "L2170"}, {"id": "resulttypes_hyperlinklistresult", "label": "HyperlinkListResult", "file_type": "code", "source_file": "D:\\Excel Add-in V2\\sources\\mcp-server-excel-main\\mcp-server-excel-main\\src\\ExcelMcp.Core\\Models\\ResultTypes.cs", "source_location": "L2208"}, {"id": "resulttypes_hyperlinkinforesult", "label": "HyperlinkInfoResult", "file_type": "code", "source_file": "D:\\Excel Add-in V2\\sources\\mcp-server-excel-main\\mcp-server-excel-main\\src\\ExcelMcp.Core\\Models\\ResultTypes.cs", "source_location": "L2229"}, {"id": "resulttypes_rangenumberformatresult", "label": "RangeNumberFormatResult", "file_type": "code", "source_file": "D:\\Excel Add-in V2\\sources\\mcp-server-excel-main\\mcp-server-excel-main\\src\\ExcelMcp.Core\\Models\\ResultTypes.cs", "source_location": "L2260"}, {"id": "resulttypes_rangevalidationresult", "label": "RangeValidationResult", "file_type": "code", "source_file": "D:\\Excel Add-in V2\\sources\\mcp-server-excel-main\\mcp-server-excel-main\\src\\ExcelMcp.Core\\Models\\ResultTypes.cs", "source_location": "L2295"}, {"id": "resulttypes_rangemergeinforesult", "label": "RangeMergeInfoResult", "file_type": "code", "source_file": "D:\\Excel Add-in V2\\sources\\mcp-server-excel-main\\mcp-server-excel-main\\src\\ExcelMcp.Core\\Models\\ResultTypes.cs", "source_location": "L2389"}, {"id": "resulttypes_rangelockinforesult", "label": "RangeLockInfoResult", "file_type": "code", "source_file": "D:\\Excel Add-in V2\\sources\\mcp-server-excel-main\\mcp-server-excel-main\\src\\ExcelMcp.Core\\Models\\ResultTypes.cs", "source_location": "L2410"}, {"id": "resulttypes_diagresult", "label": "DiagResult", "file_type": "code", "source_file": "D:\\Excel Add-in V2\\sources\\mcp-server-excel-main\\mcp-server-excel-main\\src\\ExcelMcp.Core\\Models\\ResultTypes.cs", "source_location": "L2435"}], "edges": [{"source": "d_excel_add_in_v2_sources_mcp_server_excel_main_mcp_server_excel_main_src_excelmcp_core_models_resulttypes_cs", "target": "serialization", "relation": "imports", "confidence": "EXTRACTED", "source_file": "D:\\Excel Add-in V2\\sources\\mcp-server-excel-main\\mcp-server-excel-main\\src\\ExcelMcp.Core\\Models\\ResultTypes.cs", "source_location": "L1", "weight": 1.0}, {"source": "d_excel_add_in_v2_sources_mcp_server_excel_main_mcp_server_excel_main_src_excelmcp_core_models_resulttypes_cs", "target": "resulttypes_resultbase", "relation": "contains", "confidence": "EXTRACTED", "source_file": "D:\\Excel Add-in V2\\sources\\mcp-server-excel-main\\mcp-server-excel-main\\src\\ExcelMcp.Core\\Models\\ResultTypes.cs", "source_location": "L11", "weight": 1.0}, {"source": "d_excel_add_in_v2_sources_mcp_server_excel_main_mcp_server_excel_main_src_excelmcp_core_models_resulttypes_cs", "target": "resulttypes_operationresult", "relation": "contains", "confidence": "EXTRACTED", "source_file": "D:\\Excel Add-in V2\\sources\\mcp-server-excel-main\\mcp-server-excel-main\\src\\ExcelMcp.Core\\Models\\ResultTypes.cs", "source_location": "L34", "weight": 1.0}, {"source": "resulttypes_operationresult", "target": "resulttypes_resultbase", "relation": "inherits", "confidence": "EXTRACTED", "source_file": "D:\\Excel Add-in V2\\sources\\mcp-server-excel-main\\mcp-server-excel-main\\src\\ExcelMcp.Core\\Models\\ResultTypes.cs", "source_location": "L34", "weight": 1.0}, {"source": "d_excel_add_in_v2_sources_mcp_server_excel_main_mcp_server_excel_main_src_excelmcp_core_models_resulttypes_cs", "target": "resulttypes_renameresult", "relation": "contains", "confidence": "EXTRACTED", "source_file": "D:\\Excel Add-in V2\\sources\\mcp-server-excel-main\\mcp-server-excel-main\\src\\ExcelMcp.Core\\Models\\ResultTypes.cs", "source_location": "L52", "weight": 1.0}, {"source": "resulttypes_renameresult", "target": "resulttypes_resultbase", "relation": "inherits", "confidence": "EXTRACTED", "source_file": "D:\\Excel Add-in V2\\sources\\mcp-server-excel-main\\mcp-server-excel-main\\src\\ExcelMcp.Core\\Models\\ResultTypes.cs", "source_location": "L52", "weight": 1.0}, {"source": "d_excel_add_in_v2_sources_mcp_server_excel_main_mcp_server_excel_main_src_excelmcp_core_models_resulttypes_cs", "target": "resulttypes_worksheetlistresult", "relation": "contains", "confidence": "EXTRACTED", "source_file": "D:\\Excel Add-in V2\\sources\\mcp-server-excel-main\\mcp-server-excel-main\\src\\ExcelMcp.Core\\Models\\ResultTypes.cs", "source_location": "L85", "weight": 1.0}, {"source": "resulttypes_worksheetlistresult", "target": "resulttypes_resultbase", "relation": "inherits", "confidence": "EXTRACTED", "source_file": "D:\\Excel Add-in V2\\sources\\mcp-server-excel-main\\mcp-server-excel-main\\src\\ExcelMcp.Core\\Models\\ResultTypes.cs", "source_location": "L85", "weight": 1.0}, {"source": "d_excel_add_in_v2_sources_mcp_server_excel_main_mcp_server_excel_main_src_excelmcp_core_models_resulttypes_cs", "target": "resulttypes_worksheetinfo", "relation": "contains", "confidence": "EXTRACTED", "source_file": "D:\\Excel Add-in V2\\sources\\mcp-server-excel-main\\mcp-server-excel-main\\src\\ExcelMcp.Core\\Models\\ResultTypes.cs", "source_location": "L96", "weight": 1.0}, {"source": "d_excel_add_in_v2_sources_mcp_server_excel_main_mcp_server_excel_main_src_excelmcp_core_models_resulttypes_cs", "target": "resulttypes_tabcolorresult", "relation": "contains", "confidence": "EXTRACTED", "source_file": "D:\\Excel Add-in V2\\sources\\mcp-server-excel-main\\mcp-server-excel-main\\src\\ExcelMcp.Core\\Models\\ResultTypes.cs", "source_location": "L138", "weight": 1.0}, {"source": "resulttypes_tabcolorresult", "target": "resulttypes_resultbase", "relation": "inherits", "confidence": "EXTRACTED", "source_file": "D:\\Excel Add-in V2\\sources\\mcp-server-excel-main\\mcp-server-excel-main\\src\\ExcelMcp.Core\\Models\\ResultTypes.cs", "source_location": "L138", "weight": 1.0}, {"source": "d_excel_add_in_v2_sources_mcp_server_excel_main_mcp_server_excel_main_src_excelmcp_core_models_resulttypes_cs", "target": "resulttypes_sheetvisibilityresult", "relation": "contains", "confidence": "EXTRACTED", "source_file": "D:\\Excel Add-in V2\\sources\\mcp-server-excel-main\\mcp-server-excel-main\\src\\ExcelMcp.Core\\Models\\ResultTypes.cs", "source_location": "L173", "weight": 1.0}, {"source": "resulttypes_sheetvisibilityresult", "target": "resulttypes_resultbase", "relation": "inherits", "confidence": "EXTRACTED", "source_file": "D:\\Excel Add-in V2\\sources\\mcp-server-excel-main\\mcp-server-excel-main\\src\\ExcelMcp.Core\\Models\\ResultTypes.cs", "source_location": "L173", "weight": 1.0}, {"source": "d_excel_add_in_v2_sources_mcp_server_excel_main_mcp_server_excel_main_src_excelmcp_core_models_resulttypes_cs", "target": "resulttypes_worksheetdataresult", "relation": "contains", "confidence": "EXTRACTED", "source_file": "D:\\Excel Add-in V2\\sources\\mcp-server-excel-main\\mcp-server-excel-main\\src\\ExcelMcp.Core\\Models\\ResultTypes.cs", "source_location": "L189", "weight": 1.0}, {"source": "resulttypes_worksheetdataresult", "target": "resulttypes_resultbase", "relation": "inherits", "confidence": "EXTRACTED", "source_file": "D:\\Excel Add-in V2\\sources\\mcp-server-excel-main\\mcp-server-excel-main\\src\\ExcelMcp.Core\\Models\\ResultTypes.cs", "source_location": "L189", "weight": 1.0}, {"source": "d_excel_add_in_v2_sources_mcp_server_excel_main_mcp_server_excel_main_src_excelmcp_core_models_resulttypes_cs", "target": "resulttypes_powerquerylistresult", "relation": "contains", "confidence": "EXTRACTED", "source_file": "D:\\Excel Add-in V2\\sources\\mcp-server-excel-main\\mcp-server-excel-main\\src\\ExcelMcp.Core\\Models\\ResultTypes.cs", "source_location": "L225", "weight": 1.0}, {"source": "resulttypes_powerquerylistresult", "target": "resulttypes_resultbase", "relation": "inherits", "confidence": "EXTRACTED", "source_file": "D:\\Excel Add-in V2\\sources\\mcp-server-excel-main\\mcp-server-excel-main\\src\\ExcelMcp.Core\\Models\\ResultTypes.cs", "source_location": "L225", "weight": 1.0}, {"source": "d_excel_add_in_v2_sources_mcp_server_excel_main_mcp_server_excel_main_src_excelmcp_core_models_resulttypes_cs", "target": "resulttypes_powerqueryinfo", "relation": "contains", "confidence": "EXTRACTED", "source_file": "D:\\Excel Add-in V2\\sources\\mcp-server-excel-main\\mcp-server-excel-main\\src\\ExcelMcp.Core\\Models\\ResultTypes.cs", "source_location": "L236", "weight": 1.0}, {"source": "d_excel_add_in_v2_sources_mcp_server_excel_main_mcp_server_excel_main_src_excelmcp_core_models_resulttypes_cs", "target": "resulttypes_powerqueryviewresult", "relation": "contains", "confidence": "EXTRACTED", "source_file": "D:\\Excel Add-in V2\\sources\\mcp-server-excel-main\\mcp-server-excel-main\\src\\ExcelMcp.Core\\Models\\ResultTypes.cs", "source_location": "L262", "weight": 1.0}, {"source": "resulttypes_powerqueryviewresult", "target": "resulttypes_resultbase", "relation": "inherits", "confidence": "EXTRACTED", "source_file": "D:\\Excel Add-in V2\\sources\\mcp-server-excel-main\\mcp-server-excel-main\\src\\ExcelMcp.Core\\Models\\ResultTypes.cs", "source_location": "L262", "weight": 1.0}, {"source": "d_excel_add_in_v2_sources_mcp_server_excel_main_mcp_server_excel_main_src_excelmcp_core_models_resulttypes_cs", "target": "resulttypes_powerqueryloadconfigresult", "relation": "contains", "confidence": "EXTRACTED", "source_file": "D:\\Excel Add-in V2\\sources\\mcp-server-excel-main\\mcp-server-excel-main\\src\\ExcelMcp.Core\\Models\\ResultTypes.cs", "source_location": "L319", "weight": 1.0}, {"source": "resulttypes_powerqueryloadconfigresult", "target": "resulttypes_resultbase", "relation": "inherits", "confidence": "EXTRACTED", "source_file": "D:\\Excel Add-in V2\\sources\\mcp-server-excel-main\\mcp-server-excel-main\\src\\ExcelMcp.Core\\Models\\ResultTypes.cs", "source_location": "L319", "weight": 1.0}, {"source": "d_excel_add_in_v2_sources_mcp_server_excel_main_mcp_server_excel_main_src_excelmcp_core_models_resulttypes_cs", "target": "resulttypes_powerqueryloadtodatamodelresult", "relation": "contains", "confidence": "EXTRACTED", "source_file": "D:\\Excel Add-in V2\\sources\\mcp-server-excel-main\\mcp-server-excel-main\\src\\ExcelMcp.Core\\Models\\ResultTypes.cs", "source_location": "L352", "weight": 1.0}, {"source": "resulttypes_powerqueryloadtodatamodelresult", "target": "resulttypes_operationresult", "relation": "inherits", "confidence": "EXTRACTED", "source_file": "D:\\Excel Add-in V2\\sources\\mcp-server-excel-main\\mcp-server-excel-main\\src\\ExcelMcp.Core\\Models\\ResultTypes.cs", "source_location": "L352", "weight": 1.0}, {"source": "d_excel_add_in_v2_sources_mcp_server_excel_main_mcp_server_excel_main_src_excelmcp_core_models_resulttypes_cs", "target": "resulttypes_powerqueryloadtotableresult", "relation": "contains", "confidence": "EXTRACTED", "source_file": "D:\\Excel Add-in V2\\sources\\mcp-server-excel-main\\mcp-server-excel-main\\src\\ExcelMcp.Core\\Models\\ResultTypes.cs", "source_location": "L389", "weight": 1.0}, {"source": "resulttypes_powerqueryloadtotableresult", "target": "resulttypes_operationresult", "relation": "inherits", "confidence": "EXTRACTED", "source_file": "D:\\Excel Add-in V2\\sources\\mcp-server-excel-main\\mcp-server-excel-main\\src\\ExcelMcp.Core\\Models\\ResultTypes.cs", "source_location": "L389", "weight": 1.0}, {"source": "d_excel_add_in_v2_sources_mcp_server_excel_main_mcp_server_excel_main_src_excelmcp_core_models_resulttypes_cs", "target": "resulttypes_powerqueryloadtobothresult", "relation": "contains", "confidence": "EXTRACTED", "source_file": "D:\\Excel Add-in V2\\sources\\mcp-server-excel-main\\mcp-server-excel-main\\src\\ExcelMcp.Core\\Models\\ResultTypes.cs", "source_location": "L426", "weight": 1.0}, {"source": "resulttypes_powerqueryloadtobothresult", "target": "resulttypes_operationresult", "relation": "inherits", "confidence": "EXTRACTED", "source_file": "D:\\Excel Add-in V2\\sources\\mcp-server-excel-main\\mcp-server-excel-main\\src\\ExcelMcp.Core\\Models\\ResultTypes.cs", "source_location": "L426", "weight": 1.0}, {"source": "d_excel_add_in_v2_sources_mcp_server_excel_main_mcp_server_excel_main_src_excelmcp_core_models_resulttypes_cs", "target": "resulttypes_powerquerycreateresult", "relation": "contains", "confidence": "EXTRACTED", "source_file": "D:\\Excel Add-in V2\\sources\\mcp-server-excel-main\\mcp-server-excel-main\\src\\ExcelMcp.Core\\Models\\ResultTypes.cs", "source_location": "L478", "weight": 1.0}, {"source": "resulttypes_powerquerycreateresult", "target": "resulttypes_operationresult", "relation": "inherits", "confidence": "EXTRACTED", "source_file": "D:\\Excel Add-in V2\\sources\\mcp-server-excel-main\\mcp-server-excel-main\\src\\ExcelMcp.Core\\Models\\ResultTypes.cs", "source_location": "L478", "weight": 1.0}, {"source": "d_excel_add_in_v2_sources_mcp_server_excel_main_mcp_server_excel_main_src_excelmcp_core_models_resulttypes_cs", "target": "resulttypes_powerqueryloadresult", "relation": "contains", "confidence": "EXTRACTED", "source_file": "D:\\Excel Add-in V2\\sources\\mcp-server-excel-main\\mcp-server-excel-main\\src\\ExcelMcp.Core\\Models\\ResultTypes.cs", "source_location": "L522", "weight": 1.0}, {"source": "resulttypes_powerqueryloadresult", "target": "resulttypes_operationresult", "relation": "inherits", "confidence": "EXTRACTED", "source_file": "D:\\Excel Add-in V2\\sources\\mcp-server-excel-main\\mcp-server-excel-main\\src\\ExcelMcp.Core\\Models\\ResultTypes.cs", "source_location": "L522", "weight": 1.0}, {"source": "d_excel_add_in_v2_sources_mcp_server_excel_main_mcp_server_excel_main_src_excelmcp_core_models_resulttypes_cs", "target": "resulttypes_powerqueryvalidationresult", "relation": "contains", "confidence": "EXTRACTED", "source_file": "D:\\Excel Add-in V2\\sources\\mcp-server-excel-main\\mcp-server-excel-main\\src\\ExcelMcp.Core\\Models\\ResultTypes.cs", "source_location": "L566", "weight": 1.0}, {"source": "resulttypes_powerqueryvalidationresult", "target": "resulttypes_resultbase", "relation": "inherits", "confidence": "EXTRACTED", "source_file": "D:\\Excel Add-in V2\\sources\\mcp-server-excel-main\\mcp-server-excel-main\\src\\ExcelMcp.Core\\Models\\ResultTypes.cs", "source_location": "L566", "weight": 1.0}, {"source": "d_excel_add_in_v2_sources_mcp_server_excel_main_mcp_server_excel_main_src_excelmcp_core_models_resulttypes_cs", "target": "resulttypes_namedrangelistresult", "relation": "contains", "confidence": "EXTRACTED", "source_file": "D:\\Excel Add-in V2\\sources\\mcp-server-excel-main\\mcp-server-excel-main\\src\\ExcelMcp.Core\\Models\\ResultTypes.cs", "source_location": "L588", "weight": 1.0}, {"source": "resulttypes_namedrangelistresult", "target": "resulttypes_resultbase", "relation": "inherits", "confidence": "EXTRACTED", "source_file": "D:\\Excel Add-in V2\\sources\\mcp-server-excel-main\\mcp-server-excel-main\\src\\ExcelMcp.Core\\Models\\ResultTypes.cs", "source_location": "L588", "weight": 1.0}, {"source": "d_excel_add_in_v2_sources_mcp_server_excel_main_mcp_server_excel_main_src_excelmcp_core_models_resulttypes_cs", "target": "resulttypes_namedrangeinfo", "relation": "contains", "confidence": "EXTRACTED", "source_file": "D:\\Excel Add-in V2\\sources\\mcp-server-excel-main\\mcp-server-excel-main\\src\\ExcelMcp.Core\\Models\\ResultTypes.cs", "source_location": "L599", "weight": 1.0}, {"source": "d_excel_add_in_v2_sources_mcp_server_excel_main_mcp_server_excel_main_src_excelmcp_core_models_resulttypes_cs", "target": "resulttypes_namedrangevalue", "relation": "contains", "confidence": "EXTRACTED", "source_file": "D:\\Excel Add-in V2\\sources\\mcp-server-excel-main\\mcp-server-excel-main\\src\\ExcelMcp.Core\\Models\\ResultTypes.cs", "source_location": "L626", "weight": 1.0}, {"source": "d_excel_add_in_v2_sources_mcp_server_excel_main_mcp_server_excel_main_src_excelmcp_core_models_resulttypes_cs", "target": "resulttypes_namedrangevalueresult", "relation": "contains", "confidence": "EXTRACTED", "source_file": "D:\\Excel Add-in V2\\sources\\mcp-server-excel-main\\mcp-server-excel-main\\src\\ExcelMcp.Core\\Models\\ResultTypes.cs", "source_location": "L653", "weight": 1.0}, {"source": "resulttypes_namedrangevalueresult", "target": "resulttypes_resultbase", "relation": "inherits", "confidence": "EXTRACTED", "source_file": "D:\\Excel Add-in V2\\sources\\mcp-server-excel-main\\mcp-server-excel-main\\src\\ExcelMcp.Core\\Models\\ResultTypes.cs", "source_location": "L653", "weight": 1.0}, {"source": "d_excel_add_in_v2_sources_mcp_server_excel_main_mcp_server_excel_main_src_excelmcp_core_models_resulttypes_cs", "target": "resulttypes_vbalistresult", "relation": "contains", "confidence": "EXTRACTED", "source_file": "D:\\Excel Add-in V2\\sources\\mcp-server-excel-main\\mcp-server-excel-main\\src\\ExcelMcp.Core\\Models\\ResultTypes.cs", "source_location": "L680", "weight": 1.0}, {"source": "resulttypes_vbalistresult", "target": "resulttypes_resultbase", "relation": "inherits", "confidence": "EXTRACTED", "source_file": "D:\\Excel Add-in V2\\sources\\mcp-server-excel-main\\mcp-server-excel-main\\src\\ExcelMcp.Core\\Models\\ResultTypes.cs", "source_location": "L680", "weight": 1.0}, {"source": "d_excel_add_in_v2_sources_mcp_server_excel_main_mcp_server_excel_main_src_excelmcp_core_models_resulttypes_cs", "target": "resulttypes_vbaviewresult", "relation": "contains", "confidence": "EXTRACTED", "source_file": "D:\\Excel Add-in V2\\sources\\mcp-server-excel-main\\mcp-server-excel-main\\src\\ExcelMcp.Core\\Models\\ResultTypes.cs", "source_location": "L691", "weight": 1.0}, {"source": "resulttypes_vbaviewresult", "target": "resulttypes_resultbase", "relation": "inherits", "confidence": "EXTRACTED", "source_file": "D:\\Excel Add-in V2\\sources\\mcp-server-excel-main\\mcp-server-excel-main\\src\\ExcelMcp.Core\\Models\\ResultTypes.cs", "source_location": "L691", "weight": 1.0}, {"source": "d_excel_add_in_v2_sources_mcp_server_excel_main_mcp_server_excel_main_src_excelmcp_core_models_resulttypes_cs", "target": "resulttypes_scriptinfo", "relation": "contains", "confidence": "EXTRACTED", "source_file": "D:\\Excel Add-in V2\\sources\\mcp-server-excel-main\\mcp-server-excel-main\\src\\ExcelMcp.Core\\Models\\ResultTypes.cs", "source_location": "L722", "weight": 1.0}, {"source": "d_excel_add_in_v2_sources_mcp_server_excel_main_mcp_server_excel_main_src_excelmcp_core_models_resulttypes_cs", "target": "resulttypes_filevalidationinfo", "relation": "contains", "confidence": "EXTRACTED", "source_file": "D:\\Excel Add-in V2\\sources\\mcp-server-excel-main\\mcp-server-excel-main\\src\\ExcelMcp.Core\\Models\\ResultTypes.cs", "source_location": "L748", "weight": 1.0}, {"source": "d_excel_add_in_v2_sources_mcp_server_excel_main_mcp_server_excel_main_src_excelmcp_core_models_resulttypes_cs", "target": "resulttypes_cellvalueresult", "relation": "contains", "confidence": "EXTRACTED", "source_file": "D:\\Excel Add-in V2\\sources\\mcp-server-excel-main\\mcp-server-excel-main\\src\\ExcelMcp.Core\\Models\\ResultTypes.cs", "source_location": "L798", "weight": 1.0}, {"source": "resulttypes_cellvalueresult", "target": "resulttypes_resultbase", "relation": "inherits", "confidence": "EXTRACTED", "source_file": "D:\\Excel Add-in V2\\sources\\mcp-server-excel-main\\mcp-server-excel-main\\src\\ExcelMcp.Core\\Models\\ResultTypes.cs", "source_location": "L798", "weight": 1.0}, {"source": "d_excel_add_in_v2_sources_mcp_server_excel_main_mcp_server_excel_main_src_excelmcp_core_models_resulttypes_cs", "target": "resulttypes_rangevalueresult", "relation": "contains", "confidence": "EXTRACTED", "source_file": "D:\\Excel Add-in V2\\sources\\mcp-server-excel-main\\mcp-server-excel-main\\src\\ExcelMcp.Core\\Models\\ResultTypes.cs", "source_location": "L826", "weight": 1.0}, {"source": "resulttypes_rangevalueresult", "target": "resulttypes_resultbase", "relation": "inherits", "confidence": "EXTRACTED", "source_file": "D:\\Excel Add-in V2\\sources\\mcp-server-excel-main\\mcp-server-excel-main\\src\\ExcelMcp.Core\\Models\\ResultTypes.cs", "source_location": "L826", "weight": 1.0}, {"source": "d_excel_add_in_v2_sources_mcp_server_excel_main_mcp_server_excel_main_src_excelmcp_core_models_resulttypes_cs", "target": "resulttypes_rangeformularesult", "relation": "contains", "confidence": "EXTRACTED", "source_file": "D:\\Excel Add-in V2\\sources\\mcp-server-excel-main\\mcp-server-excel-main\\src\\ExcelMcp.Core\\Models\\ResultTypes.cs", "source_location": "L857", "weight": 1.0}, {"source": "resulttypes_rangeformularesult", "target": "resulttypes_resultbase", "relation": "inherits", "confidence": "EXTRACTED", "source_file": "D:\\Excel Add-in V2\\sources\\mcp-server-excel-main\\mcp-server-excel-main\\src\\ExcelMcp.Core\\Models\\ResultTypes.cs", "source_location": "L857", "weight": 1.0}, {"source": "d_excel_add_in_v2_sources_mcp_server_excel_main_mcp_server_excel_main_src_excelmcp_core_models_resulttypes_cs", "target": "resulttypes_rangecellerror", "relation": "contains", "confidence": "EXTRACTED", "source_file": "D:\\Excel Add-in V2\\sources\\mcp-server-excel-main\\mcp-server-excel-main\\src\\ExcelMcp.Core\\Models\\ResultTypes.cs", "source_location": "L900", "weight": 1.0}, {"source": "d_excel_add_in_v2_sources_mcp_server_excel_main_mcp_server_excel_main_src_excelmcp_core_models_resulttypes_cs", "target": "resulttypes_rangeformulavalidationresult", "relation": "contains", "confidence": "EXTRACTED", "source_file": "D:\\Excel Add-in V2\\sources\\mcp-server-excel-main\\mcp-server-excel-main\\src\\ExcelMcp.Core\\Models\\ResultTypes.cs", "source_location": "L944", "weight": 1.0}, {"source": "resulttypes_rangeformulavalidationresult", "target": "resulttypes_resultbase", "relation": "inherits", "confidence": "EXTRACTED", "source_file": "D:\\Excel Add-in V2\\sources\\mcp-server-excel-main\\mcp-server-excel-main\\src\\ExcelMcp.Core\\Models\\ResultTypes.cs", "source_location": "L944", "weight": 1.0}, {"source": "d_excel_add_in_v2_sources_mcp_server_excel_main_mcp_server_excel_main_src_excelmcp_core_models_resulttypes_cs", "target": "resulttypes_formulavalidationerror", "relation": "contains", "confidence": "EXTRACTED", "source_file": "D:\\Excel Add-in V2\\sources\\mcp-server-excel-main\\mcp-server-excel-main\\src\\ExcelMcp.Core\\Models\\ResultTypes.cs", "source_location": "L997", "weight": 1.0}, {"source": "d_excel_add_in_v2_sources_mcp_server_excel_main_mcp_server_excel_main_src_excelmcp_core_models_resulttypes_cs", "target": "resulttypes_formulavalidationwarning", "relation": "contains", "confidence": "EXTRACTED", "source_file": "D:\\Excel Add-in V2\\sources\\mcp-server-excel-main\\mcp-server-excel-main\\src\\ExcelMcp.Core\\Models\\ResultTypes.cs", "source_location": "L1039", "weight": 1.0}, {"source": "d_excel_add_in_v2_sources_mcp_server_excel_main_mcp_server_excel_main_src_excelmcp_core_models_resulttypes_cs", "target": "resulttypes_rangefindresult", "relation": "contains", "confidence": "EXTRACTED", "source_file": "D:\\Excel Add-in V2\\sources\\mcp-server-excel-main\\mcp-server-excel-main\\src\\ExcelMcp.Core\\Models\\ResultTypes.cs", "source_location": "L1065", "weight": 1.0}, {"source": "resulttypes_rangefindresult", "target": "resulttypes_resultbase", "relation": "inherits", "confidence": "EXTRACTED", "source_file": "D:\\Excel Add-in V2\\sources\\mcp-server-excel-main\\mcp-server-excel-main\\src\\ExcelMcp.Core\\Models\\ResultTypes.cs", "source_location": "L1065", "weight": 1.0}, {"source": "d_excel_add_in_v2_sources_mcp_server_excel_main_mcp_server_excel_main_src_excelmcp_core_models_resulttypes_cs", "target": "resulttypes_rangecell", "relation": "contains", "confidence": "EXTRACTED", "source_file": "D:\\Excel Add-in V2\\sources\\mcp-server-excel-main\\mcp-server-excel-main\\src\\ExcelMcp.Core\\Models\\ResultTypes.cs", "source_location": "L1091", "weight": 1.0}, {"source": "d_excel_add_in_v2_sources_mcp_server_excel_main_mcp_server_excel_main_src_excelmcp_core_models_resulttypes_cs", "target": "resulttypes_rangeinforesult", "relation": "contains", "confidence": "EXTRACTED", "source_file": "D:\\Excel Add-in V2\\sources\\mcp-server-excel-main\\mcp-server-excel-main\\src\\ExcelMcp.Core\\Models\\ResultTypes.cs", "source_location": "L1118", "weight": 1.0}, {"source": "resulttypes_rangeinforesult", "target": "resulttypes_resultbase", "relation": "inherits", "confidence": "EXTRACTED", "source_file": "D:\\Excel Add-in V2\\sources\\mcp-server-excel-main\\mcp-server-excel-main\\src\\ExcelMcp.Core\\Models\\ResultTypes.cs", "source_location": "L1118", "weight": 1.0}, {"source": "d_excel_add_in_v2_sources_mcp_server_excel_main_mcp_server_excel_main_src_excelmcp_core_models_resulttypes_cs", "target": "resulttypes_rangehyperlinkresult", "relation": "contains", "confidence": "EXTRACTED", "source_file": "D:\\Excel Add-in V2\\sources\\mcp-server-excel-main\\mcp-server-excel-main\\src\\ExcelMcp.Core\\Models\\ResultTypes.cs", "source_location": "L1174", "weight": 1.0}, {"source": "resulttypes_rangehyperlinkresult", "target": "resulttypes_resultbase", "relation": "inherits", "confidence": "EXTRACTED", "source_file": "D:\\Excel Add-in V2\\sources\\mcp-server-excel-main\\mcp-server-excel-main\\src\\ExcelMcp.Core\\Models\\ResultTypes.cs", "source_location": "L1174", "weight": 1.0}, {"source": "d_excel_add_in_v2_sources_mcp_server_excel_main_mcp_server_excel_main_src_excelmcp_core_models_resulttypes_cs", "target": "resulttypes_rangestyleresult", "relation": "contains", "confidence": "EXTRACTED", "source_file": "D:\\Excel Add-in V2\\sources\\mcp-server-excel-main\\mcp-server-excel-main\\src\\ExcelMcp.Core\\Models\\ResultTypes.cs", "source_location": "L1195", "weight": 1.0}, {"source": "resulttypes_rangestyleresult", "target": "resulttypes_resultbase", "relation": "inherits", "confidence": "EXTRACTED", "source_file": "D:\\Excel Add-in V2\\sources\\mcp-server-excel-main\\mcp-server-excel-main\\src\\ExcelMcp.Core\\Models\\ResultTypes.cs", "source_location": "L1195", "weight": 1.0}, {"source": "d_excel_add_in_v2_sources_mcp_server_excel_main_mcp_server_excel_main_src_excelmcp_core_models_resulttypes_cs", "target": "resulttypes_vbatrustresult", "relation": "contains", "confidence": "EXTRACTED", "source_file": "D:\\Excel Add-in V2\\sources\\mcp-server-excel-main\\mcp-server-excel-main\\src\\ExcelMcp.Core\\Models\\ResultTypes.cs", "source_location": "L1227", "weight": 1.0}, {"source": "resulttypes_vbatrustresult", "target": "resulttypes_resultbase", "relation": "inherits", "confidence": "EXTRACTED", "source_file": "D:\\Excel Add-in V2\\sources\\mcp-server-excel-main\\mcp-server-excel-main\\src\\ExcelMcp.Core\\Models\\ResultTypes.cs", "source_location": "L1227", "weight": 1.0}, {"source": "d_excel_add_in_v2_sources_mcp_server_excel_main_mcp_server_excel_main_src_excelmcp_core_models_resulttypes_cs", "target": "resulttypes_powerqueryrefreshresult", "relation": "contains", "confidence": "EXTRACTED", "source_file": "D:\\Excel Add-in V2\\sources\\mcp-server-excel-main\\mcp-server-excel-main\\src\\ExcelMcp.Core\\Models\\ResultTypes.cs", "source_location": "L1283", "weight": 1.0}, {"source": "resulttypes_powerqueryrefreshresult", "target": "resulttypes_resultbase", "relation": "inherits", "confidence": "EXTRACTED", "source_file": "D:\\Excel Add-in V2\\sources\\mcp-server-excel-main\\mcp-server-excel-main\\src\\ExcelMcp.Core\\Models\\ResultTypes.cs", "source_location": "L1283", "weight": 1.0}, {"source": "d_excel_add_in_v2_sources_mcp_server_excel_main_mcp_server_excel_main_src_excelmcp_core_models_resulttypes_cs", "target": "resulttypes_powerqueryerrorcheckresult", "relation": "contains", "confidence": "EXTRACTED", "source_file": "D:\\Excel Add-in V2\\sources\\mcp-server-excel-main\\mcp-server-excel-main\\src\\ExcelMcp.Core\\Models\\ResultTypes.cs", "source_location": "L1320", "weight": 1.0}, {"source": "resulttypes_powerqueryerrorcheckresult", "target": "resulttypes_resultbase", "relation": "inherits", "confidence": "EXTRACTED", "source_file": "D:\\Excel Add-in V2\\sources\\mcp-server-excel-main\\mcp-server-excel-main\\src\\ExcelMcp.Core\\Models\\ResultTypes.cs", "source_location": "L1320", "weight": 1.0}, {"source": "d_excel_add_in_v2_sources_mcp_server_excel_main_mcp_server_excel_main_src_excelmcp_core_models_resulttypes_cs", "target": "resulttypes_powerqueryevaluateresult", "relation": "contains", "confidence": "EXTRACTED", "source_file": "D:\\Excel Add-in V2\\sources\\mcp-server-excel-main\\mcp-server-excel-main\\src\\ExcelMcp.Core\\Models\\ResultTypes.cs", "source_location": "L1358", "weight": 1.0}, {"source": "resulttypes_powerqueryevaluateresult", "target": "resulttypes_resultbase", "relation": "inherits", "confidence": "EXTRACTED", "source_file": "D:\\Excel Add-in V2\\sources\\mcp-server-excel-main\\mcp-server-excel-main\\src\\ExcelMcp.Core\\Models\\ResultTypes.cs", "source_location": "L1358", "weight": 1.0}, {"source": "d_excel_add_in_v2_sources_mcp_server_excel_main_mcp_server_excel_main_src_excelmcp_core_models_resulttypes_cs", "target": "resulttypes_connectionlistresult", "relation": "contains", "confidence": "EXTRACTED", "source_file": "D:\\Excel Add-in V2\\sources\\mcp-server-excel-main\\mcp-server-excel-main\\src\\ExcelMcp.Core\\Models\\ResultTypes.cs", "source_location": "L1391", "weight": 1.0}, {"source": "resulttypes_connectionlistresult", "target": "resulttypes_resultbase", "relation": "inherits", "confidence": "EXTRACTED", "source_file": "D:\\Excel Add-in V2\\sources\\mcp-server-excel-main\\mcp-server-excel-main\\src\\ExcelMcp.Core\\Models\\ResultTypes.cs", "source_location": "L1391", "weight": 1.0}, {"source": "d_excel_add_in_v2_sources_mcp_server_excel_main_mcp_server_excel_main_src_excelmcp_core_models_resulttypes_cs", "target": "resulttypes_connectioninfo", "relation": "contains", "confidence": "EXTRACTED", "source_file": "D:\\Excel Add-in V2\\sources\\mcp-server-excel-main\\mcp-server-excel-main\\src\\ExcelMcp.Core\\Models\\ResultTypes.cs", "source_location": "L1402", "weight": 1.0}, {"source": "d_excel_add_in_v2_sources_mcp_server_excel_main_mcp_server_excel_main_src_excelmcp_core_models_resulttypes_cs", "target": "resulttypes_connectionviewresult", "relation": "contains", "confidence": "EXTRACTED", "source_file": "D:\\Excel Add-in V2\\sources\\mcp-server-excel-main\\mcp-server-excel-main\\src\\ExcelMcp.Core\\Models\\ResultTypes.cs", "source_location": "L1445", "weight": 1.0}, {"source": "resulttypes_connectionviewresult", "target": "resulttypes_resultbase", "relation": "inherits", "confidence": "EXTRACTED", "source_file": "D:\\Excel Add-in V2\\sources\\mcp-server-excel-main\\mcp-server-excel-main\\src\\ExcelMcp.Core\\Models\\ResultTypes.cs", "source_location": "L1445", "weight": 1.0}, {"source": "d_excel_add_in_v2_sources_mcp_server_excel_main_mcp_server_excel_main_src_excelmcp_core_models_resulttypes_cs", "target": "resulttypes_connectionpropertiesresult", "relation": "contains", "confidence": "EXTRACTED", "source_file": "D:\\Excel Add-in V2\\sources\\mcp-server-excel-main\\mcp-server-excel-main\\src\\ExcelMcp.Core\\Models\\ResultTypes.cs", "source_location": "L1488", "weight": 1.0}, {"source": "resulttypes_connectionpropertiesresult", "target": "resulttypes_resultbase", "relation": "inherits", "confidence": "EXTRACTED", "source_file": "D:\\Excel Add-in V2\\sources\\mcp-server-excel-main\\mcp-server-excel-main\\src\\ExcelMcp.Core\\Models\\ResultTypes.cs", "source_location": "L1488", "weight": 1.0}, {"source": "d_excel_add_in_v2_sources_mcp_server_excel_main_mcp_server_excel_main_src_excelmcp_core_models_resulttypes_cs", "target": "resulttypes_datamodeltablelistresult", "relation": "contains", "confidence": "EXTRACTED", "source_file": "D:\\Excel Add-in V2\\sources\\mcp-server-excel-main\\mcp-server-excel-main\\src\\ExcelMcp.Core\\Models\\ResultTypes.cs", "source_location": "L1523", "weight": 1.0}, {"source": "resulttypes_datamodeltablelistresult", "target": "resulttypes_resultbase", "relation": "inherits", "confidence": "EXTRACTED", "source_file": "D:\\Excel Add-in V2\\sources\\mcp-server-excel-main\\mcp-server-excel-main\\src\\ExcelMcp.Core\\Models\\ResultTypes.cs", "source_location": "L1523", "weight": 1.0}, {"source": "d_excel_add_in_v2_sources_mcp_server_excel_main_mcp_server_excel_main_src_excelmcp_core_models_resulttypes_cs", "target": "resulttypes_datamodeltableinfo", "relation": "contains", "confidence": "EXTRACTED", "source_file": "D:\\Excel Add-in V2\\sources\\mcp-server-excel-main\\mcp-server-excel-main\\src\\ExcelMcp.Core\\Models\\ResultTypes.cs", "source_location": "L1534", "weight": 1.0}, {"source": "d_excel_add_in_v2_sources_mcp_server_excel_main_mcp_server_excel_main_src_excelmcp_core_models_resulttypes_cs", "target": "resulttypes_datamodelmeasurelistresult", "relation": "contains", "confidence": "EXTRACTED", "source_file": "D:\\Excel Add-in V2\\sources\\mcp-server-excel-main\\mcp-server-excel-main\\src\\ExcelMcp.Core\\Models\\ResultTypes.cs", "source_location": "L1555", "weight": 1.0}, {"source": "resulttypes_datamodelmeasurelistresult", "target": "resulttypes_resultbase", "relation": "inherits", "confidence": "EXTRACTED", "source_file": "D:\\Excel Add-in V2\\sources\\mcp-server-excel-main\\mcp-server-excel-main\\src\\ExcelMcp.Core\\Models\\ResultTypes.cs", "source_location": "L1555", "weight": 1.0}, {"source": "d_excel_add_in_v2_sources_mcp_server_excel_main_mcp_server_excel_main_src_excelmcp_core_models_resulttypes_cs", "target": "resulttypes_datamodelmeasureinfo", "relation": "contains", "confidence": "EXTRACTED", "source_file": "D:\\Excel Add-in V2\\sources\\mcp-server-excel-main\\mcp-server-excel-main\\src\\ExcelMcp.Core\\Models\\ResultTypes.cs", "source_location": "L1566", "weight": 1.0}, {"source": "d_excel_add_in_v2_sources_mcp_server_excel_main_mcp_server_excel_main_src_excelmcp_core_models_resulttypes_cs", "target": "resulttypes_measureformatinfo", "relation": "contains", "confidence": "EXTRACTED", "source_file": "D:\\Excel Add-in V2\\sources\\mcp-server-excel-main\\mcp-server-excel-main\\src\\ExcelMcp.Core\\Models\\ResultTypes.cs", "source_location": "L1594", "weight": 1.0}, {"source": "d_excel_add_in_v2_sources_mcp_server_excel_main_mcp_server_excel_main_src_excelmcp_core_models_resulttypes_cs", "target": "resulttypes_datamodelmeasureviewresult", "relation": "contains", "confidence": "EXTRACTED", "source_file": "D:\\Excel Add-in V2\\sources\\mcp-server-excel-main\\mcp-server-excel-main\\src\\ExcelMcp.Core\\Models\\ResultTypes.cs", "source_location": "L1623", "weight": 1.0}, {"source": "resulttypes_datamodelmeasureviewresult", "target": "resulttypes_resultbase", "relation": "inherits", "confidence": "EXTRACTED", "source_file": "D:\\Excel Add-in V2\\sources\\mcp-server-excel-main\\mcp-server-excel-main\\src\\ExcelMcp.Core\\Models\\ResultTypes.cs", "source_location": "L1623", "weight": 1.0}, {"source": "d_excel_add_in_v2_sources_mcp_server_excel_main_mcp_server_excel_main_src_excelmcp_core_models_resulttypes_cs", "target": "resulttypes_datamodelrelationshiplistresult", "relation": "contains", "confidence": "EXTRACTED", "source_file": "D:\\Excel Add-in V2\\sources\\mcp-server-excel-main\\mcp-server-excel-main\\src\\ExcelMcp.Core\\Models\\ResultTypes.cs", "source_location": "L1662", "weight": 1.0}, {"source": "resulttypes_datamodelrelationshiplistresult", "target": "resulttypes_resultbase", "relation": "inherits", "confidence": "EXTRACTED", "source_file": "D:\\Excel Add-in V2\\sources\\mcp-server-excel-main\\mcp-server-excel-main\\src\\ExcelMcp.Core\\Models\\ResultTypes.cs", "source_location": "L1662", "weight": 1.0}, {"source": "d_excel_add_in_v2_sources_mcp_server_excel_main_mcp_server_excel_main_src_excelmcp_core_models_resulttypes_cs", "target": "resulttypes_datamodelrelationshipviewresult", "relation": "contains", "confidence": "EXTRACTED", "source_file": "D:\\Excel Add-in V2\\sources\\mcp-server-excel-main\\mcp-server-excel-main\\src\\ExcelMcp.Core\\Models\\ResultTypes.cs", "source_location": "L1673", "weight": 1.0}, {"source": "resulttypes_datamodelrelationshipviewresult", "target": "resulttypes_resultbase", "relation": "inherits", "confidence": "EXTRACTED", "source_file": "D:\\Excel Add-in V2\\sources\\mcp-server-excel-main\\mcp-server-excel-main\\src\\ExcelMcp.Core\\Models\\ResultTypes.cs", "source_location": "L1673", "weight": 1.0}, {"source": "d_excel_add_in_v2_sources_mcp_server_excel_main_mcp_server_excel_main_src_excelmcp_core_models_resulttypes_cs", "target": "resulttypes_datamodelrelationshipinfo", "relation": "contains", "confidence": "EXTRACTED", "source_file": "D:\\Excel Add-in V2\\sources\\mcp-server-excel-main\\mcp-server-excel-main\\src\\ExcelMcp.Core\\Models\\ResultTypes.cs", "source_location": "L1685", "weight": 1.0}, {"source": "d_excel_add_in_v2_sources_mcp_server_excel_main_mcp_server_excel_main_src_excelmcp_core_models_resulttypes_cs", "target": "resulttypes_datamodelvalidationresult", "relation": "contains", "confidence": "EXTRACTED", "source_file": "D:\\Excel Add-in V2\\sources\\mcp-server-excel-main\\mcp-server-excel-main\\src\\ExcelMcp.Core\\Models\\ResultTypes.cs", "source_location": "L1716", "weight": 1.0}, {"source": "resulttypes_datamodelvalidationresult", "target": "resulttypes_resultbase", "relation": "inherits", "confidence": "EXTRACTED", "source_file": "D:\\Excel Add-in V2\\sources\\mcp-server-excel-main\\mcp-server-excel-main\\src\\ExcelMcp.Core\\Models\\ResultTypes.cs", "source_location": "L1716", "weight": 1.0}, {"source": "d_excel_add_in_v2_sources_mcp_server_excel_main_mcp_server_excel_main_src_excelmcp_core_models_resulttypes_cs", "target": "resulttypes_datamodelcalculatedcolumnlistresult", "relation": "contains", "confidence": "EXTRACTED", "source_file": "D:\\Excel Add-in V2\\sources\\mcp-server-excel-main\\mcp-server-excel-main\\src\\ExcelMcp.Core\\Models\\ResultTypes.cs", "source_location": "L1738", "weight": 1.0}, {"source": "resulttypes_datamodelcalculatedcolumnlistresult", "target": "resulttypes_resultbase", "relation": "inherits", "confidence": "EXTRACTED", "source_file": "D:\\Excel Add-in V2\\sources\\mcp-server-excel-main\\mcp-server-excel-main\\src\\ExcelMcp.Core\\Models\\ResultTypes.cs", "source_location": "L1738", "weight": 1.0}, {"source": "d_excel_add_in_v2_sources_mcp_server_excel_main_mcp_server_excel_main_src_excelmcp_core_models_resulttypes_cs", "target": "resulttypes_datamodelcalculatedcolumninfo", "relation": "contains", "confidence": "EXTRACTED", "source_file": "D:\\Excel Add-in V2\\sources\\mcp-server-excel-main\\mcp-server-excel-main\\src\\ExcelMcp.Core\\Models\\ResultTypes.cs", "source_location": "L1749", "weight": 1.0}, {"source": "d_excel_add_in_v2_sources_mcp_server_excel_main_mcp_server_excel_main_src_excelmcp_core_models_resulttypes_cs", "target": "resulttypes_datamodelcalculatedcolumnviewresult", "relation": "contains", "confidence": "EXTRACTED", "source_file": "D:\\Excel Add-in V2\\sources\\mcp-server-excel-main\\mcp-server-excel-main\\src\\ExcelMcp.Core\\Models\\ResultTypes.cs", "source_location": "L1781", "weight": 1.0}, {"source": "resulttypes_datamodelcalculatedcolumnviewresult", "target": "resulttypes_resultbase", "relation": "inherits", "confidence": "EXTRACTED", "source_file": "D:\\Excel Add-in V2\\sources\\mcp-server-excel-main\\mcp-server-excel-main\\src\\ExcelMcp.Core\\Models\\ResultTypes.cs", "source_location": "L1781", "weight": 1.0}, {"source": "d_excel_add_in_v2_sources_mcp_server_excel_main_mcp_server_excel_main_src_excelmcp_core_models_resulttypes_cs", "target": "resulttypes_daxevaluateresult", "relation": "contains", "confidence": "EXTRACTED", "source_file": "D:\\Excel Add-in V2\\sources\\mcp-server-excel-main\\mcp-server-excel-main\\src\\ExcelMcp.Core\\Models\\ResultTypes.cs", "source_location": "L1818", "weight": 1.0}, {"source": "resulttypes_daxevaluateresult", "target": "resulttypes_resultbase", "relation": "inherits", "confidence": "EXTRACTED", "source_file": "D:\\Excel Add-in V2\\sources\\mcp-server-excel-main\\mcp-server-excel-main\\src\\ExcelMcp.Core\\Models\\ResultTypes.cs", "source_location": "L1818", "weight": 1.0}, {"source": "d_excel_add_in_v2_sources_mcp_server_excel_main_mcp_server_excel_main_src_excelmcp_core_models_resulttypes_cs", "target": "resulttypes_dmvqueryresult", "relation": "contains", "confidence": "EXTRACTED", "source_file": "D:\\Excel Add-in V2\\sources\\mcp-server-excel-main\\mcp-server-excel-main\\src\\ExcelMcp.Core\\Models\\ResultTypes.cs", "source_location": "L1849", "weight": 1.0}, {"source": "resulttypes_dmvqueryresult", "target": "resulttypes_resultbase", "relation": "inherits", "confidence": "EXTRACTED", "source_file": "D:\\Excel Add-in V2\\sources\\mcp-server-excel-main\\mcp-server-excel-main\\src\\ExcelMcp.Core\\Models\\ResultTypes.cs", "source_location": "L1849", "weight": 1.0}, {"source": "d_excel_add_in_v2_sources_mcp_server_excel_main_mcp_server_excel_main_src_excelmcp_core_models_resulttypes_cs", "target": "resulttypes_tabledaxinforesult", "relation": "contains", "confidence": "EXTRACTED", "source_file": "D:\\Excel Add-in V2\\sources\\mcp-server-excel-main\\mcp-server-excel-main\\src\\ExcelMcp.Core\\Models\\ResultTypes.cs", "source_location": "L1880", "weight": 1.0}, {"source": "resulttypes_tabledaxinforesult", "target": "resulttypes_resultbase", "relation": "inherits", "confidence": "EXTRACTED", "source_file": "D:\\Excel Add-in V2\\sources\\mcp-server-excel-main\\mcp-server-excel-main\\src\\ExcelMcp.Core\\Models\\ResultTypes.cs", "source_location": "L1880", "weight": 1.0}, {"source": "d_excel_add_in_v2_sources_mcp_server_excel_main_mcp_server_excel_main_src_excelmcp_core_models_resulttypes_cs", "target": "resulttypes_tablelistresult", "relation": "contains", "confidence": "EXTRACTED", "source_file": "D:\\Excel Add-in V2\\sources\\mcp-server-excel-main\\mcp-server-excel-main\\src\\ExcelMcp.Core\\Models\\ResultTypes.cs", "source_location": "L1912", "weight": 1.0}, {"source": "resulttypes_tablelistresult", "target": "resulttypes_resultbase", "relation": "inherits", "confidence": "EXTRACTED", "source_file": "D:\\Excel Add-in V2\\sources\\mcp-server-excel-main\\mcp-server-excel-main\\src\\ExcelMcp.Core\\Models\\ResultTypes.cs", "source_location": "L1912", "weight": 1.0}, {"source": "d_excel_add_in_v2_sources_mcp_server_excel_main_mcp_server_excel_main_src_excelmcp_core_models_resulttypes_cs", "target": "resulttypes_tableinforesult", "relation": "contains", "confidence": "EXTRACTED", "source_file": "D:\\Excel Add-in V2\\sources\\mcp-server-excel-main\\mcp-server-excel-main\\src\\ExcelMcp.Core\\Models\\ResultTypes.cs", "source_location": "L1923", "weight": 1.0}, {"source": "resulttypes_tableinforesult", "target": "resulttypes_resultbase", "relation": "inherits", "confidence": "EXTRACTED", "source_file": "D:\\Excel Add-in V2\\sources\\mcp-server-excel-main\\mcp-server-excel-main\\src\\ExcelMcp.Core\\Models\\ResultTypes.cs", "source_location": "L1923", "weight": 1.0}, {"source": "d_excel_add_in_v2_sources_mcp_server_excel_main_mcp_server_excel_main_src_excelmcp_core_models_resulttypes_cs", "target": "resulttypes_tableinfo", "relation": "contains", "confidence": "EXTRACTED", "source_file": "D:\\Excel Add-in V2\\sources\\mcp-server-excel-main\\mcp-server-excel-main\\src\\ExcelMcp.Core\\Models\\ResultTypes.cs", "source_location": "L1935", "weight": 1.0}, {"source": "d_excel_add_in_v2_sources_mcp_server_excel_main_mcp_server_excel_main_src_excelmcp_core_models_resulttypes_cs", "target": "resulttypes_tabledataresult", "relation": "contains", "confidence": "EXTRACTED", "source_file": "D:\\Excel Add-in V2\\sources\\mcp-server-excel-main\\mcp-server-excel-main\\src\\ExcelMcp.Core\\Models\\ResultTypes.cs", "source_location": "L1987", "weight": 1.0}, {"source": "resulttypes_tabledataresult", "target": "resulttypes_resultbase", "relation": "inherits", "confidence": "EXTRACTED", "source_file": "D:\\Excel Add-in V2\\sources\\mcp-server-excel-main\\mcp-server-excel-main\\src\\ExcelMcp.Core\\Models\\ResultTypes.cs", "source_location": "L1987", "weight": 1.0}, {"source": "d_excel_add_in_v2_sources_mcp_server_excel_main_mcp_server_excel_main_src_excelmcp_core_models_resulttypes_cs", "target": "resulttypes_tablefilterresult", "relation": "contains", "confidence": "EXTRACTED", "source_file": "D:\\Excel Add-in V2\\sources\\mcp-server-excel-main\\mcp-server-excel-main\\src\\ExcelMcp.Core\\Models\\ResultTypes.cs", "source_location": "L2018", "weight": 1.0}, {"source": "resulttypes_tablefilterresult", "target": "resulttypes_resultbase", "relation": "inherits", "confidence": "EXTRACTED", "source_file": "D:\\Excel Add-in V2\\sources\\mcp-server-excel-main\\mcp-server-excel-main\\src\\ExcelMcp.Core\\Models\\ResultTypes.cs", "source_location": "L2018", "weight": 1.0}, {"source": "d_excel_add_in_v2_sources_mcp_server_excel_main_mcp_server_excel_main_src_excelmcp_core_models_resulttypes_cs", "target": "resulttypes_columnfilter", "relation": "contains", "confidence": "EXTRACTED", "source_file": "D:\\Excel Add-in V2\\sources\\mcp-server-excel-main\\mcp-server-excel-main\\src\\ExcelMcp.Core\\Models\\ResultTypes.cs", "source_location": "L2039", "weight": 1.0}, {"source": "d_excel_add_in_v2_sources_mcp_server_excel_main_mcp_server_excel_main_src_excelmcp_core_models_resulttypes_cs", "target": "resulttypes_tablestructuredreferenceresult", "relation": "contains", "confidence": "EXTRACTED", "source_file": "D:\\Excel Add-in V2\\sources\\mcp-server-excel-main\\mcp-server-excel-main\\src\\ExcelMcp.Core\\Models\\ResultTypes.cs", "source_location": "L2103", "weight": 1.0}, {"source": "resulttypes_tablestructuredreferenceresult", "target": "resulttypes_resultbase", "relation": "inherits", "confidence": "EXTRACTED", "source_file": "D:\\Excel Add-in V2\\sources\\mcp-server-excel-main\\mcp-server-excel-main\\src\\ExcelMcp.Core\\Models\\ResultTypes.cs", "source_location": "L2103", "weight": 1.0}, {"source": "d_excel_add_in_v2_sources_mcp_server_excel_main_mcp_server_excel_main_src_excelmcp_core_models_resulttypes_cs", "target": "resulttypes_tablesortcolumn", "relation": "contains", "confidence": "EXTRACTED", "source_file": "D:\\Excel Add-in V2\\sources\\mcp-server-excel-main\\mcp-server-excel-main\\src\\ExcelMcp.Core\\Models\\ResultTypes.cs", "source_location": "L2150", "weight": 1.0}, {"source": "d_excel_add_in_v2_sources_mcp_server_excel_main_mcp_server_excel_main_src_excelmcp_core_models_resulttypes_cs", "target": "resulttypes_hyperlinkinfo", "relation": "contains", "confidence": "EXTRACTED", "source_file": "D:\\Excel Add-in V2\\sources\\mcp-server-excel-main\\mcp-server-excel-main\\src\\ExcelMcp.Core\\Models\\ResultTypes.cs", "source_location": "L2170", "weight": 1.0}, {"source": "d_excel_add_in_v2_sources_mcp_server_excel_main_mcp_server_excel_main_src_excelmcp_core_models_resulttypes_cs", "target": "resulttypes_hyperlinklistresult", "relation": "contains", "confidence": "EXTRACTED", "source_file": "D:\\Excel Add-in V2\\sources\\mcp-server-excel-main\\mcp-server-excel-main\\src\\ExcelMcp.Core\\Models\\ResultTypes.cs", "source_location": "L2208", "weight": 1.0}, {"source": "resulttypes_hyperlinklistresult", "target": "resulttypes_resultbase", "relation": "inherits", "confidence": "EXTRACTED", "source_file": "D:\\Excel Add-in V2\\sources\\mcp-server-excel-main\\mcp-server-excel-main\\src\\ExcelMcp.Core\\Models\\ResultTypes.cs", "source_location": "L2208", "weight": 1.0}, {"source": "d_excel_add_in_v2_sources_mcp_server_excel_main_mcp_server_excel_main_src_excelmcp_core_models_resulttypes_cs", "target": "resulttypes_hyperlinkinforesult", "relation": "contains", "confidence": "EXTRACTED", "source_file": "D:\\Excel Add-in V2\\sources\\mcp-server-excel-main\\mcp-server-excel-main\\src\\ExcelMcp.Core\\Models\\ResultTypes.cs", "source_location": "L2229", "weight": 1.0}, {"source": "resulttypes_hyperlinkinforesult", "target": "resulttypes_resultbase", "relation": "inherits", "confidence": "EXTRACTED", "source_file": "D:\\Excel Add-in V2\\sources\\mcp-server-excel-main\\mcp-server-excel-main\\src\\ExcelMcp.Core\\Models\\ResultTypes.cs", "source_location": "L2229", "weight": 1.0}, {"source": "d_excel_add_in_v2_sources_mcp_server_excel_main_mcp_server_excel_main_src_excelmcp_core_models_resulttypes_cs", "target": "resulttypes_rangenumberformatresult", "relation": "contains", "confidence": "EXTRACTED", "source_file": "D:\\Excel Add-in V2\\sources\\mcp-server-excel-main\\mcp-server-excel-main\\src\\ExcelMcp.Core\\Models\\ResultTypes.cs", "source_location": "L2260", "weight": 1.0}, {"source": "resulttypes_rangenumberformatresult", "target": "resulttypes_resultbase", "relation": "inherits", "confidence": "EXTRACTED", "source_file": "D:\\Excel Add-in V2\\sources\\mcp-server-excel-main\\mcp-server-excel-main\\src\\ExcelMcp.Core\\Models\\ResultTypes.cs", "source_location": "L2260", "weight": 1.0}, {"source": "d_excel_add_in_v2_sources_mcp_server_excel_main_mcp_server_excel_main_src_excelmcp_core_models_resulttypes_cs", "target": "resulttypes_rangevalidationresult", "relation": "contains", "confidence": "EXTRACTED", "source_file": "D:\\Excel Add-in V2\\sources\\mcp-server-excel-main\\mcp-server-excel-main\\src\\ExcelMcp.Core\\Models\\ResultTypes.cs", "source_location": "L2295", "weight": 1.0}, {"source": "resulttypes_rangevalidationresult", "target": "resulttypes_resultbase", "relation": "inherits", "confidence": "EXTRACTED", "source_file": "D:\\Excel Add-in V2\\sources\\mcp-server-excel-main\\mcp-server-excel-main\\src\\ExcelMcp.Core\\Models\\ResultTypes.cs", "source_location": "L2295", "weight": 1.0}, {"source": "d_excel_add_in_v2_sources_mcp_server_excel_main_mcp_server_excel_main_src_excelmcp_core_models_resulttypes_cs", "target": "resulttypes_rangemergeinforesult", "relation": "contains", "confidence": "EXTRACTED", "source_file": "D:\\Excel Add-in V2\\sources\\mcp-server-excel-main\\mcp-server-excel-main\\src\\ExcelMcp.Core\\Models\\ResultTypes.cs", "source_location": "L2389", "weight": 1.0}, {"source": "resulttypes_rangemergeinforesult", "target": "resulttypes_resultbase", "relation": "inherits", "confidence": "EXTRACTED", "source_file": "D:\\Excel Add-in V2\\sources\\mcp-server-excel-main\\mcp-server-excel-main\\src\\ExcelMcp.Core\\Models\\ResultTypes.cs", "source_location": "L2389", "weight": 1.0}, {"source": "d_excel_add_in_v2_sources_mcp_server_excel_main_mcp_server_excel_main_src_excelmcp_core_models_resulttypes_cs", "target": "resulttypes_rangelockinforesult", "relation": "contains", "confidence": "EXTRACTED", "source_file": "D:\\Excel Add-in V2\\sources\\mcp-server-excel-main\\mcp-server-excel-main\\src\\ExcelMcp.Core\\Models\\ResultTypes.cs", "source_location": "L2410", "weight": 1.0}, {"source": "resulttypes_rangelockinforesult", "target": "resulttypes_resultbase", "relation": "inherits", "confidence": "EXTRACTED", "source_file": "D:\\Excel Add-in V2\\sources\\mcp-server-excel-main\\mcp-server-excel-main\\src\\ExcelMcp.Core\\Models\\ResultTypes.cs", "source_location": "L2410", "weight": 1.0}, {"source": "d_excel_add_in_v2_sources_mcp_server_excel_main_mcp_server_excel_main_src_excelmcp_core_models_resulttypes_cs", "target": "resulttypes_diagresult", "relation": "contains", "confidence": "EXTRACTED", "source_file": "D:\\Excel Add-in V2\\sources\\mcp-server-excel-main\\mcp-server-excel-main\\src\\ExcelMcp.Core\\Models\\ResultTypes.cs", "source_location": "L2435", "weight": 1.0}, {"source": "resulttypes_diagresult", "target": "resulttypes_resultbase", "relation": "inherits", "confidence": "EXTRACTED", "source_file": "D:\\Excel Add-in V2\\sources\\mcp-server-excel-main\\mcp-server-excel-main\\src\\ExcelMcp.Core\\Models\\ResultTypes.cs", "source_location": "L2435", "weight": 1.0}], "raw_calls": []}